Workbook

Sheet Mode d'emploi
A1: PROVITRES-64 — CALENDRIER ÉDITORIAL SEO : 10 PAGES PAR JOUR
A2: 1307 pages et articles du 28/09/2026 au 05/02/2027 (19 semaines), 10 par jour, 70 par semaine. Site : www.nettoyage-vitres-bayonne.fr. Zone : Pays Basque et Sud Landes (233 communes).
A4: La stratégie en 4 règles
A5: 1. Une seule page forte par ville, qui vise tous les mots-clés : nettoyage, lavage, laveur, nettoyeur de vitres, fenêtres, vitrerie. Google les considère comme une même recherche : une page par synonyme se ferait concurrence à elle-même.
A6: 2. Les villages de moins de 1 000 habitants sont regroupés par secteur (même code postal) ou cités sur la page de la ville voisine (colonne « Communes à citer »). Les 233 communes sont couvertes.
A7: 3. Les pages différentes, ce sont les métiers : mairies, immeubles, vitres en hauteur, hôtels, commerces, bureaux, syndics, conciergeries, écoles… × ville. C'est là que se trouvent les clients B2B.
A8: 4. Les vitres en hauteur sont l'argument n°1 sur toutes les pages pros : perche à eau pure jusqu'à 13 m, nacelle, formation au travail en hauteur.
A10: Ordre de publication (B2B d'abord)
A11: 1 · Piliers B2B (sem. 1) : une page par métier, par service (hauteur, immeuble, nacelle, façade vitrée, verrière, entreprise de nettoyage de vitres, fenêtres, vitrerie…) et par intercommunalité (CA Pays Basque, Seignanx, MACS, Grand Dax, Orthe et Arrigans).
A12: 2 · Pages villes (sem. 1–3) : 90 villes de plus de 1 000 hab., par population décroissante, + 14 pages de secteur pour les villages. Les 18 pages « lavage-vitres-[ville] » déjà en ligne sont à OPTIMISER, pas à recréer.
A13: 3 · Pages pros par ville (sem. 3–4) : « Entreprise nettoyage vitres [ville] », villes de plus de 2 000 hab.
A14: 4 · Métier × ville (sem. 4–14) : « Nettoyage vitres mairie Anglet », « Nettoyage vitres immeuble Biarritz », « Nettoyage vitres en hauteur Bayonne »…
... A28: • Search Console limite les demandes d'indexation manuelles à une dizaine par jour : le rythme du plan colle à cette limite.

Sheet Tableau de bord
A1: TABLEAU DE BORD SEO
A3: Aujourd'hui | B3: =COUNTIF('Calendrier SEO'!$B$2:$B$1308,TODAY()) | C3: pages/articles prévus
A4: En retard | B4: =COUNTIFS('Calendrier SEO'!$B$2:$B$1308,"<"&TODAY(),'Calendrier SEO'!$Y$2:$Y$1308,"À créer")+COUNTIFS('Calendrier SEO'!$B$2:$B$1308,"<"&TODAY(),'Calendrier SEO'!$Y$2:$Y$1308,"Rédigée") | C4: non mis en ligne alors que la date est passée
A6: Par phase
A7: Phase | B7: Prévu | C7: En ligne | D7: Indexées | E7: % indexé
A8: 1 · Piliers B2B | B8: =COUNTIF('Calendrier SEO'!$F$2:$F$1308,$A8) | C8: =COUNTIFS('Calendrier SEO'!$F$2:$F$1308,$A8,'Calendrier SEO'!$Y$2:$Y$1308,"En ligne")+COUNTIFS('Calendrier SEO'!$F$2:$F$1308,$A8,'Calendrier SEO'!$Y$2:$Y$1308,"Indexation demandée")+COUNTIFS('Calendrier SEO'!$F$2:$F$1308,$A8,'Calendrier SEO'!$Y$2:$Y$1308,"Indexée")+COUNTIFS('Calendrier SEO'!$F$2:$F$1308,$A8,'Calendrier SEO'!$Y$2:$Y$1308,"Non indexée") | D8: =COUNTIFS('Calendrier SEO'!$F$2:$F$1308,$A8,'Calendrier SEO'!$Y$2:$Y$1308,"Indexée") | E8: =IFERROR(D8/B8,0)
A9: 2 · Pages villes (1 par ville) | B9: =COUNTIF('Calendrier SEO'!$F$2:$F$1308,$A9) | C9: =COUNTIFS('Calendrier SEO'!$F$2:$F$1308,$A9,'Calendrier SEO'!$Y$2:$Y$1308,"En ligne")+COUNTIFS('Calendrier SEO'!$F$2:$F$1308,$A9,'Calendrier SEO'!$Y$2:$Y$1308,"Indexation demandée")+COUNTIFS('Calendrier SEO'!$F$2:$F$1308,$A9,'Calendrier SEO'!$Y$2:$Y$1308,"Indexée")+COUNTIFS('Calendrier SEO'!$F$2:$F$1308,$A9,'Calendrier SEO'!$Y$2:$Y$1308,"Non indexée") | D9: =COUNTIFS('Calendrier SEO'!$F$2:$F$1308,$A9,'Calendrier SEO'!$Y$2:$Y$1308,"Indexée") | E9: =IFERROR(D9/B9,0)
A10: 3 · Pages pros par ville | B10: =COUNTIF('Calendrier SEO'!$F$2:$F$1308,$A10) | C10: =COUNTIFS('Calendrier SEO'!$F$2:$F$1308,$A10,'Calendrier SEO'!$Y$2:$Y$1308,"En ligne")+COUNTIFS('Calendrier SEO'!$F$2:$F$1308,$A10,'Calendrier SEO'!$Y$2:$Y$1308,"Indexation demandée")+COUNTIFS('Calendrier SEO'!$F$2:$F$1308,$A10,'Calendrier SEO'!$Y$2:$Y$1308,"Indexée")+COUNTIFS('Calendrier SEO'!$F$2:$F$1308,$A10,'Calendrier SEO'!$Y$2:$Y$1308,"Non indexée") | D10: =COUNTIFS('Calendrier SEO'!$F$2:$F$1308,$A10,'Calendrier SEO'!$Y$2:$Y$1308,"Indexée") | E10: =IFERROR(D10/B10,0)
A11: 4 · Métier × ville | B11: =COUNTIF('Calendrier SEO'!$F$2:$F$1308,$A11) | C11: =COUNTIFS('Calendrier SEO'!$F$2:$F$1308,$A11,'Calendrier SEO'!$Y$2:$Y$1308,"En ligne")+COUNTIFS('Calendrier SEO'!$F$2:$F$1308,$A11,'Calendrier SEO'!$Y$2:$Y$1308,"Indexation demandée")+COUNTIFS('Calendrier SEO'!$F$2:$F$1308,$A11,'Calendrier SEO'!$Y$2:$Y$1308,"Indexée")+COUNTIFS('Calendrier SEO'!$F$2:$F$1308,$A11,'Calendrier SEO'!$Y$2:$Y$1308,"Non indexée") | D11: =COUNTIFS('Calendrier SEO'!$F$2:$F$1308,$A11,'Calendrier SEO'!$Y$2:$Y$1308,"Indexée") | E11: =IFERROR(D11/B11,0)
A12: 5 · Panneaux solaires × ville | B12: =COUNTIF('Calendrier SEO'!$F$2:$F$1308,$A12) | C12: =COUNTIFS('Calendrier SEO'!$F$2:$F$1308,$A12,'Calendrier SEO'!$Y$2:$Y$1308,"En ligne")+COUNTIFS('Calendrier SEO'!$F$2:$F$1308,$A12,'Calendrier SEO'!$Y$2:$Y$1308,"Indexation demandée")+COUNTIFS('Calendrier SEO'!$F$2:$F$1308,$A12,'Calendrier SEO'!$Y$2:$Y$1308,"Indexée")+COUNTIFS('Calendrier SEO'!$F$2:$F$1308,$A12,'Calendrier SEO'!$Y$2:$Y$1308,"Non indexée") | D12: =COUNTIFS('Calendrier SEO'!$F$2:$F$1308,$A12,'Calendrier SEO'!$Y$2:$Y$1308,"Indexée") | E12: =IFERROR(D12/B12,0)
A13: 6 · Particuliers | B13: =COUNTIF('Calendrier SEO'!$F$2:$F$1308,$A13) | C13: =COUNTIFS('Calendrier SEO'!$F$2:$F$1308,$A13,'Calendrier SEO'!$Y$2:$Y$1308,"En ligne")+COUNTIFS('Calendrier SEO'!$F$2:$F$1308,$A13,'Calendrier SEO'!$Y$2:$Y$1308,"Indexation demandée")+COUNTIFS('Calendrier SEO'!$F$2:$F$1308,$A13,'Calendrier SEO'!$Y$2:$Y$1308,"Indexée")+COUNTIFS('Calendrier SEO'!$F$2:$F$1308,$A13,'Calendrier SEO'!$Y$2:$Y$1308,"Non indexée") | D13: =COUNTIFS('Calendrier SEO'!$F$2:$F$1308,$A13,'Calendrier SEO'!$Y$2:$Y$1308,"Indexée") | E13: =IFERROR(D13/B13,0)
A14: Articles | B14: =COUNTIF('Calendrier SEO'!$F$2:$F$1308,$A14) | C14: =COUNTIFS('Calendrier SEO'!$F$2:$F$1308,$A14,'Calendrier SEO'!$Y$2:$Y$1308,"En ligne")+COUNTIFS('Calendrier SEO'!$F$2:$F$1308,$A14,'Calendrier SEO'!$Y$2:$Y$1308,"Indexation demandée")+COUNTIFS('Calendrier SEO'!$F$2:$F$1308,$A14,'Calendrier SEO'!$Y$2:$Y$1308,"Indexée")+COUNTIFS('Calendrier SEO'!$F$2:$F$1308,$A14,'Calendrier SEO'!$Y$2:$Y$1308,"Non indexée") | D14: =COUNTIFS('Calendrier SEO'!$F$2:$F$1308,$A14,'Calendrier SEO'!$Y$2:$Y$1308,"Indexée") | E14: =IFERROR(D14/B14,0)
A15: TOTAL | B15: =SUM(B8:B14) | C15: =SUM(C8:C14) | D15: =SUM(D8:D14) | E15: =IFERROR(D15/B15,0)
A17: Par semaine
A18: Semaine | B18: Du | C18: Prévu | D18: En ligne | E18: Indexées | F18: % en ligne
A19: S01 | B19: 46293 | C19: =COUNTIF('Calendrier SEO'!$D$2:$D$1308,$A19) | D19: =COUNTIFS('Calendrier SEO'!$D$2:$D$1308,$A19,'Calendrier SEO'!$Y$2:$Y$1308,"En ligne")+COUNTIFS('Calendrier SEO'!$D$2:$D$1308,$A19,'Calendrier SEO'!$Y$2:$Y$1308,"Indexation demandée")+COUNTIFS('Calendrier SEO'!$D$2:$D$1308,$A19,'Calendrier SEO'!$Y$2:$Y$1308,"Indexée")+COUNTIFS('Calendrier SEO'!$D$2:$D$1308,$A19,'Calendrier SEO'!$Y$2:$Y$1308,"Non indexée") | E19: =COUNTIFS('Calendrier SEO'!$D$2:$D$1308,$A19,'Calendrier SEO'!$Y$2:$Y$1308,"Indexée") | F19: =IFERROR(D19/C19,0)
A20: S02 | B20: 46300 | C20: =COUNTIF('Calendrier SEO'!$D$2:$D$1308,$A20) | D20: =COUNTIFS('Calendrier SEO'!$D$2:$D$1308,$A20,'Calendrier SEO'!$Y$2:$Y$1308,"En ligne")+COUNTIFS('Calendrier SEO'!$D$2:$D$1308,$A20,'Calendrier SEO'!$Y$2:$Y$1308,"Indexation demandée")+COUNTIFS('Calendrier SEO'!$D$2:$D$1308,$A20,'Calendrier SEO'!$Y$2:$Y$1308,"Indexée")+COUNTIFS('Calendrier SEO'!$D$2:$D$1308,$A20,'Calendrier SEO'!$Y$2:$Y$1308,"Non indexée") | E20: =COUNTIFS('Calendrier SEO'!$D$2:$D$1308,$A20,'Calendrier SEO'!$Y$2:$Y$1308,"Indexée") | F20: =IFERROR(D20/C20,0)
A21: S03 | B21: 46307 | C21: =COUNTIF('Calendrier SEO'!$D$2:$D$1308,$A21) | D21: =COUNTIFS('Calendrier SEO'!$D$2:$D$1308,$A21,'Calendrier SEO'!$Y$2:$Y$1308,"En ligne")+COUNTIFS('Calendrier SEO'!$D$2:$D$1308,$A21,'Calendrier SEO'!$Y$2:$Y$1308,"Indexation demandée")+COUNTIFS('Calendrier SEO'!$D$2:$D$1308,$A21,'Calendrier SEO'!$Y$2:$Y$1308,"Indexée")+COUNTIFS('Calendrier SEO'!$D$2:$D$1308,$A21,'Calendrier SEO'!$Y$2:$Y$1308,"Non indexée") | E21: =COUNTIFS('Calendrier SEO'!$D$2:$D$1308,$A21,'Calendrier SEO'!$Y$2:$Y$1308,"Indexée") | F21: =IFERROR(D21/C21,0)
A22: S04 | B22: 46314 | C22: =COUNTIF('Calendrier SEO'!$D$2:$D$1308,$A22) | D22: =COUNTIFS('Calendrier SEO'!$D$2:$D$1308,$A22,'Calendrier SEO'!$Y$2:$Y$1308,"En ligne")+COUNTIFS('Calendrier SEO'!$D$2:$D$1308,$A22,'Calendrier SEO'!$Y$2:$Y$1308,"Indexation demandée")+COUNTIFS('Calendrier SEO'!$D$2:$D$1308,$A22,'Calendrier SEO'!$Y$2:$Y$1308,"Indexée")+COUNTIFS('Calendrier SEO'!$D$2:$D$1308,$A22,'Calendrier SEO'!$Y$2:$Y$1308,"Non indexée") | E22: =COUNTIFS('Calendrier SEO'!$D$2:$D$1308,$A22,'Calendrier SEO'!$Y$2:$Y$1308,"Indexée") | F22: =IFERROR(D22/C22,0)
A23: S05 | B23: 46321 | C23: =COUNTIF('Calendrier SEO'!$D$2:$D$1308,$A23) | D23: =COUNTIFS('Calendrier SEO'!$D$2:$D$1308,$A23,'Calendrier SEO'!$Y$2:$Y$1308,"En ligne")+COUNTIFS('Calendrier SEO'!$D$2:$D$1308,$A23,'Calendrier SEO'!$Y$2:$Y$1308,"Indexation demandée")+COUNTIFS('Calendrier SEO'!$D$2:$D$1308,$A23,'Calendrier SEO'!$Y$2:$Y$1308,"Indexée")+COUNTIFS('Calendrier SEO'!$D$2:$D$1308,$A23,'Calendrier SEO'!$Y$2:$Y$1308,"Non indexée") | E23: =COUNTIFS('Calendrier SEO'!$D$2:$D$1308,$A23,'Calendrier SEO'!$Y$2:$Y$1308,"Indexée") | F23: =IFERROR(D23/C23,0)
A24: S06 | B24: 46328 | C24: =COUNTIF('Calendrier SEO'!$D$2:$D$1308,$A24) | D24: =COUNTIFS('Calendrier SEO'!$D$2:$D$1308,$A24,'Calendrier SEO'!$Y$2:$Y$1308,"En ligne")+COUNTIFS('Calendrier SEO'!$D$2:$D$1308,$A24,'Calendrier SEO'!$Y$2:$Y$1308,"Indexation demandée")+COUNTIFS('Calendrier SEO'!$D$2:$D$1308,$A24,'Calendrier SEO'!$Y$2:$Y$1308,"Indexée")+COUNTIFS('Calendrier SEO'!$D$2:$D$1308,$A24,'Calendrier SEO'!$Y$2:$Y$1308,"Non indexée") | E24: =COUNTIFS('Calendrier SEO'!$D$2:$D$1308,$A24,'Calendrier SEO'!$Y$2:$Y$1308,"Indexée") | F24: =IFERROR(D24/C24,0)
A25: S07 | B25: 46335 | C25: =COUNTIF('Calendrier SEO'!$D$2:$D$1308,$A25) | D25: =COUNTIFS('Calendrier SEO'!$D$2:$D$1308,$A25,'Calendrier SEO'!$Y$2:$Y$1308,"En ligne")+COUNTIFS('Calendrier SEO'!$D$2:$D$1308,$A25,'Calendrier SEO'!$Y$2:$Y$1308,"Indexation demandée")+COUNTIFS('Calendrier SEO'!$D$2:$D$1308,$A25,'Calendrier SEO'!$Y$2:$Y$1308,"Indexée")+COUNTIFS('Calendrier SEO'!$D$2:$D$1308,$A25,'Calendrier SEO'!$Y$2:$Y$1308,"Non indexée") | E25: =COUNTIFS('Calendrier SEO'!$D$2:$D$1308,$A25,'Calendrier SEO'!$Y$2:$Y$1308,"Indexée") | F25: =IFERROR(D25/C25,0)
A26: S08 | B26: 46342 | C26: =COUNTIF('Calendrier SEO'!$D$2:$D$1308,$A26) | D26: =COUNTIFS('Calendrier SEO'!$D$2:$D$1308,$A26,'Calendrier SEO'!$Y$2:$Y$1308,"En ligne")+COUNTIFS('Calendrier SEO'!$D$2:$D$1308,$A26,'Calendrier SEO'!$Y$2:$Y$1308,"Indexation demandée")+COUNTIFS('Calendrier SEO'!$D$2:$D$1308,$A26,'Calendrier SEO'!$Y$2:$Y$1308,"Indexée")+COUNTIFS('Calendrier SEO'!$D$2:$D$1308,$A26,'Calendrier SEO'!$Y$2:$Y$1308,"Non indexée") | E26: =COUNTIFS('Calendrier SEO'!$D$2:$D$1308,$A26,'Calendrier SEO'!$Y$2:$Y$1308,"Indexée") | F26: =IFERROR(D26/C26,0)
A27: S09 | B27: 46349 | C27: =COUNTIF('Calendrier SEO'!$D$2:$D$1308,$A27) | D27: =COUNTIFS('Calendrier SEO'!$D$2:$D$1308,$A27,'Calendrier SEO'!$Y$2:$Y$1308,"En ligne")+COUNTIFS('Calendrier SEO'!$D$2:$D$1308,$A27,'Calendrier SEO'!$Y$2:$Y$1308,"Indexation demandée")+COUNTIFS('Calendrier SEO'!$D$2:$D$1308,$A27,'Calendrier SEO'!$Y$2:$Y$1308,"Indexée")+COUNTIFS('Calendrier SEO'!$D$2:$D$1308,$A27,'Calendrier SEO'!$Y$2:$Y$1308,"Non indexée") | E27: =COUNTIFS('Calendrier SEO'!$D$2:$D$1308,$A27,'Calendrier SEO'!$Y$2:$Y$1308,"Indexée") | F27: =IFERROR(D27/C27,0)
A28: S10 | B28: 46356 | C28: =COUNTIF('Calendrier SEO'!$D$2:$D$1308,$A28) | D28: =COUNTIFS('Calendrier SEO'!$D$2:$D$1308,$A28,'Calendrier SEO'!$Y$2:$Y$1308,"En ligne")+COUNTIFS('Calendrier SEO'!$D$2:$D$1308,$A28,'Calendrier SEO'!$Y$2:$Y$1308,"Indexation demandée")+COUNTIFS('Calendrier SEO'!$D$2:$D$1308,$A28,'Calendrier SEO'!$Y$2:$Y$1308,"Indexée")+COUNTIFS('Calendrier SEO'!$D$2:$D$1308,$A28,'Calendrier SEO'!$Y$2:$Y$1308,"Non indexée") | E28: =COUNTIFS('Calendrier SEO'!$D$2:$D$1308,$A28,'Calendrier SEO'!$Y$2:$Y$1308,"Indexée") | F28: =IFERROR(D28/C28,0)
A29: S11 | B29: 46363 | C29: =COUNTIF('Calendrier SEO'!$D$2:$D$1308,$A29) | D29: =COUNTIFS('Calendrier SEO'!$D$2:$D$1308,$A29,'Calendrier SEO'!$Y$2:$Y$1308,"En ligne")+COUNTIFS('Calendrier SEO'!$D$2:$D$1308,$A29,'Calendrier SEO'!$Y$2:$Y$1308,"Indexation demandée")+COUNTIFS('Calendrier SEO'!$D$2:$D$1308,$A29,'Calendrier SEO'!$Y$2:$Y$1308,"Indexée")+COUNTIFS('Calendrier SEO'!$D$2:$D$1308,$A29,'Calendrier SEO'!$Y$2:$Y$1308,"Non indexée") | E29: =COUNTIFS('Calendrier SEO'!$D$2:$D$1308,$A29,'Calendrier SEO'!$Y$2:$Y$1308,"Indexée") | F29: =IFERROR(D29/C29,0)
A30: S12 | B30: 46370 | C30: =COUNTIF('Calendrier SEO'!$D$2:$D$1308,$A30) | D30: =COUNTIFS('Calendrier SEO'!$D$2:$D$1308,$A30,'Calendrier SEO'!$Y$2:$Y$1308,"En ligne")+COUNTIFS('Calendrier SEO'!$D$2:$D$1308,$A30,'Calendrier SEO'!$Y$2:$Y$1308,"Indexation demandée")+COUNTIFS('Calendrier SEO'!$D$2:$D$1308,$A30,'Calendrier SEO'!$Y$2:$Y$1308,"Indexée")+COUNTIFS('Calendrier SEO'!$D$2:$D$1308,$A30,'Calendrier SEO'!$Y$2:$Y$1308,"Non indexée") | E30: =COUNTIFS('Calendrier SEO'!$D$2:$D$1308,$A30,'Calendrier SEO'!$Y$2:$Y$1308,"Indexée") | F30: =IFERROR(D30/C30,0)
... A37: S19 | B37: 46419 | C37: =COUNTIF('Calendrier SEO'!$D$2:$D$1308,$A37) | D37: =COUNTIFS('Calendrier SEO'!$D$2:$D$1308,$A37,'Calendrier SEO'!$Y$2:$Y$1308,"En ligne")+COUNTIFS('Calendrier SEO'!$D$2:$D$1308,$A37,'Calendrier SEO'!$Y$2:$Y$1308,"Indexation demandée")+COUNTIFS('Calendrier SEO'!$D$2:$D$1308,$A37,'Calendrier SEO'!$Y$2:$Y$1308,"Indexée")+COUNTIFS('Calendrier SEO'!$D$2:$D$1308,$A37,'Calendrier SEO'!$Y$2:$Y$1308,"Non indexée") | E37: =COUNTIFS('Calendrier SEO'!$D$2:$D$1308,$A37,'Calendrier SEO'!$Y$2:$Y$1308,"Indexée") | F37: =IFERROR(D37/C37,0)

Sheet Calendrier SEO
A1: N° | B1: Date | C1: Jour | D1: Semaine | E1: Type | F1: Phase | G1: Cible | H1: Catégorie | I1: Ville | J1: Population | K1: Zone | L1: Segment / service | M1: Mot-clé principal | N1: Mots-clés secondaires | O1: Title SEO | P1: Meta description | Q1: H1 | R1: Plan H2 | S1: Angle local (contenu unique) | T1: Point fort à mettre en avant | U1: Communes à citer | V1: Slug (URL) | W1: URL complète | X1: Liens internes | Y1: Statut | Z1: Date mise en ligne | AA1: Indexation demandée le | AB1: Indexée ? | AC1: Notes
A2: 1 | B2: 46293 | C2: Lundi | D2: S01 | E2: Page hors menu | F2: 1 · Piliers B2B | G2: B2B | H2: Page pilier métier | L2: Mairies & bâtiments communaux | M2: Nettoyage vitres mairie Pays Basque | N2: lavage vitres mairie Landes, laveur de vitres mairies, nettoyeur de vitres professionnel | O2: Nettoyage vitres mairie Pays Basque & Sud Landes | P2: Nettoyage vitres mairie au Pays Basque et dans le Sud Landes pour vos bâtiments communaux : lavage à l'eau pure, vitres en hauteur jusqu'à 13 m, contrat… | Q2: Nettoyage vitres mairie au Pays Basque et dans le Sud Landes | R2: Pourquoi confier vos bâtiments communaux à un laveur de vitres pro | Ce que nous nettoyons | Vitres en hauteur : perche à eau pure jusqu'à 13 m, nacelle si besoin | Fréquence et contrat d'entretien | Villes desservies | Devis gratuit | T2: Devis par bâtiment, facturation Chorus Pro, interventions pendant les vacances scolaires | V2: nettoyage-vitres-mairie-pays-basque | W2: ="https://www.nettoyage-vitres-bayonne.fr/"&V2 | X2: service-de-nettoyage-professionnels, contact-devis | Y2: Rédigée | AC2: Page générée le 27/09/2026 — à mettre en ligne
A3: 2 | B3: 46293 | C3: Lundi | D3: S01 | E3: Page hors menu | F3: 1 · Piliers B2B | G3: B2B | H3: Page pilier métier | L3: Immeubles & copropriétés | M3: Nettoyage vitres immeuble Pays Basque | N3: lavage vitres immeuble Landes, laveur de vitres immeubles, nettoyeur de vitres professionnel | O3: Nettoyage vitres immeuble Pays Basque & Sud Landes | P3: Nettoyage vitres immeuble au Pays Basque et dans le Sud Landes pour votre immeuble : lavage à l'eau pure, vitres en hauteur jusqu'à 13 m, contrat sur… | Q3: Nettoyage vitres immeuble au Pays Basque et dans le Sud Landes | R3: Pourquoi confier votre immeuble à un laveur de vitres pro | Ce que nous nettoyons | Vitres en hauteur : perche à eau pure jusqu'à 13 m, nacelle si besoin | Fréquence et contrat d'entretien | Villes desservies | Devis gratuit | T3: Façades et parties communes en hauteur sans nacelle (perche 13 m), facture par immeuble pour les syndics | V3: nettoyage-vitres-immeuble-pays-basque | W3: ="https://www.nettoyage-vitres-bayonne.fr/"&V3 | X3: service-de-nettoyage-professionnels, contact-devis | Y3: Rédigée | AC3: Page générée le 27/09/2026 — à mettre en ligne
A4: 3 | B4: 46293 | C4: Lundi | D4: S01 | E4: Page hors menu | F4: 1 · Piliers B2B | G4: B2B | H4: Page pilier métier | L4: Vitres en hauteur | M4: Nettoyage vitres en hauteur Pays Basque | N4: lavage vitres en hauteur Landes, laveur de vitres vitres, nettoyeur de vitres professionnel | O4: Nettoyage vitres en hauteur Pays Basque & Sud Landes | P4: Nettoyage vitres en hauteur au Pays Basque et dans le Sud Landes pour vos vitres en hauteur : lavage à l'eau pure, vitres en hauteur jusqu'à 13 m, contrat… | Q4: Nettoyage vitres en hauteur au Pays Basque et dans le Sud Landes | R4: Pourquoi confier vos vitres en hauteur à un laveur de vitres pro | Ce que nous nettoyons | Vitres en hauteur : perche à eau pure jusqu'à 13 m, nacelle si besoin | Fréquence et contrat d'entretien | Villes desservies | Devis gratuit | T4: Perche télescopique eau pure 13 m, nacelle, formation travail en hauteur | V4: nettoyage-vitres-en-hauteur-pays-basque | W4: ="https://www.nettoyage-vitres-bayonne.fr/"&V4 | X4: service-de-nettoyage-professionnels, contact-devis | Y4: Rédigée | AC4: Page générée le 27/09/2026 — à mettre en ligne
A5: 4 | B5: 46293 | C5: Lundi | D5: S01 | E5: Page hors menu | F5: 1 · Piliers B2B | G5: B2B | H5: Page pilier métier | L5: Commerces & boutiques | M5: Nettoyage vitrine magasin Pays Basque | N5: lavage vitrine magasin Landes, laveur de vitres commerces, nettoyeur de vitres professionnel | O5: Nettoyage vitrine magasin Pays Basque & Sud Landes | P5: Nettoyage vitrine magasin au Pays Basque et dans le Sud Landes pour votre commerce : lavage à l'eau pure, vitres en hauteur jusqu'à 13 m, contrat sur… | Q5: Nettoyage vitrine magasin au Pays Basque et dans le Sud Landes | R5: Pourquoi confier votre commerce à un laveur de vitres pro | Ce que nous nettoyons | Vitres en hauteur : perche à eau pure jusqu'à 13 m, nacelle si besoin | Fréquence et contrat d'entretien | Villes desservies | Devis gratuit | T5: Passage avant l'ouverture, abonnement vitrine, tournée à vélo | V5: nettoyage-vitrine-magasin-pays-basque | W5: ="https://www.nettoyage-vitres-bayonne.fr/"&V5 | X5: service-de-nettoyage-professionnels, contact-devis | Y5: Rédigée | AC5: Page générée le 27/09/2026 — à mettre en ligne
A6: 5 | B6: 46293 | C6: Lundi | D6: S01 | E6: Page hors menu | F6: 1 · Piliers B2B | G6: B2B | H6: Page pilier métier | L6: Hôtels & résidences | M6: Nettoyage vitres hôtel Pays Basque | N6: lavage vitres hôtel Landes, laveur de vitres hôtels, nettoyeur de vitres professionnel | O6: Nettoyage vitres hôtel Pays Basque & Sud Landes | P6: Nettoyage vitres hôtel au Pays Basque et dans le Sud Landes pour votre hôtel : lavage à l'eau pure, vitres en hauteur jusqu'à 13 m, contrat sur mesure.… | Q6: Nettoyage vitres hôtel au Pays Basque et dans le Sud Landes | R6: Pourquoi confier votre hôtel à un laveur de vitres pro | Ce que nous nettoyons | Vitres en hauteur : perche à eau pure jusqu'à 13 m, nacelle si besoin | Fréquence et contrat d'entretien | Villes desservies | Devis gratuit | T6: Façades et baies des chambres en hauteur, interventions hors affluence, renfort avant la saison | V6: nettoyage-vitres-hotel-pays-basque | W6: ="https://www.nettoyage-vitres-bayonne.fr/"&V6 | X6: service-de-nettoyage-professionnels, contact-devis | Y6: Rédigée | AC6: Page générée le 27/09/2026 — à mettre en ligne
A7: 6 | B7: 46293 | C7: Lundi | D7: S01 | E7: Page hors menu | F7: 1 · Piliers B2B | G7: B2B | H7: Page pilier métier | L7: Bureaux & entreprises | M7: Nettoyage vitres bureaux Pays Basque | N7: lavage vitres bureaux Landes, laveur de vitres bureaux, nettoyeur de vitres professionnel | O7: Nettoyage vitres bureaux Pays Basque & Sud Landes | P7: Nettoyage vitres bureaux au Pays Basque et dans le Sud Landes pour vos bureaux : lavage à l'eau pure, vitres en hauteur jusqu'à 13 m, contrat sur mesure.… | Q7: Nettoyage vitres bureaux au Pays Basque et dans le Sud Landes | R7: Pourquoi confier vos bureaux à un laveur de vitres pro | Ce que nous nettoyons | Vitres en hauteur : perche à eau pure jusqu'à 13 m, nacelle si besoin | Fréquence et contrat d'entretien | Villes desservies | Devis gratuit | T7: Contrat d'entretien, interventions hors horaires, façades vitrées | V7: nettoyage-vitres-bureaux-pays-basque | W7: ="https://www.nettoyage-vitres-bayonne.fr/"&V7 | X7: service-de-nettoyage-professionnels, contact-devis | Y7: Rédigée | AC7: Page générée le 27/09/2026 — à mettre en ligne
A8: 7 | B8: 46293 | C8: Lundi | D8: S01 | E8: Page hors menu | F8: 1 · Piliers B2B | G8: B2B | H8: Page pilier métier | L8: Restaurants, bars & cafés | M8: Nettoyage vitres restaurant Pays Basque | N8: lavage vitres restaurant Landes, laveur de vitres restaurants,, nettoyeur de vitres professionnel | O8: Nettoyage vitres restaurant Pays Basque & Sud Landes | P8: Nettoyage vitres restaurant au Pays Basque et dans le Sud Landes pour votre restaurant : lavage à l'eau pure, vitres en hauteur jusqu'à 13 m, contrat sur… | Q8: Nettoyage vitres restaurant au Pays Basque et dans le Sud Landes | R8: Pourquoi confier votre restaurant à un laveur de vitres pro | Ce que nous nettoyons | Vitres en hauteur : perche à eau pure jusqu'à 13 m, nacelle si besoin | Fréquence et contrat d'entretien | Villes desservies | Devis gratuit | T8: Vitrine et terrasse vitrée propres avant le service | V8: nettoyage-vitres-restaurant-pays-basque | W8: ="https://www.nettoyage-vitres-bayonne.fr/"&V8 | X8: service-de-nettoyage-professionnels, contact-devis | Y8: Rédigée | AC8: Page générée le 27/09/2026 — à mettre en ligne
A9: 8 | B9: 46293 | C9: Lundi | D9: S01 | E9: Page hors menu | F9: 1 · Piliers B2B | G9: B2B | H9: Page pilier métier | L9: Conciergeries & locations saisonnières | M9: Nettoyage vitres location saisonnière Pays Basque | N9: lavage vitres location saisonnière Landes, laveur de vitres conciergeries, nettoyeur de vitres professionnel | O9: Nettoyage vitres location saisonnière Pays Basque & Sud Landes | P9: Nettoyage vitres location saisonnière au Pays Basque et dans le Sud Landes pour vos locations saisonnières : lavage à l'eau pure, vitres en hauteur… | Q9: Nettoyage vitres location saisonnière au Pays Basque et dans le Sud Landes | R9: Pourquoi confier vos locations saisonnières à un laveur de vitres pro | Ce que nous nettoyons | Vitres en hauteur : perche à eau pure jusqu'à 13 m, nacelle si besoin | Fréquence et contrat d'entretien | Villes desservies | Devis gratuit | T9: Passages entre deux séjours, baies vitrées face à la mer | V9: nettoyage-vitres-location-saisonniere-pays-basque | W9: ="https://www.nettoyage-vitres-bayonne.fr/"&V9 | X9: service-de-nettoyage-professionnels, contact-devis | Y9: Rédigée | AC9: Page générée le 27/09/2026 — à mettre en ligne
A10: 9 | B10: 46293 | C10: Lundi | D10: S01 | E10: Article | F10: Articles | G10: B2B | H10: Article vitres en hauteur / immeubles | L10: Vitres en hauteur | M10: nettoyage vitres en hauteur | O10: Nettoyage de vitres en hauteur : perche à eau pure ou | P10: Nettoyage de vitres en hauteur : perche à eau pure ou nacelle ? — les conseils de ProVitres-64, laveur de vitres professionnel au Pays Basque et dans le… | Q10: Nettoyage de vitres en hauteur : perche à eau pure ou nacelle ? | R10: Introduction | Le problème | Les solutions | Notre méthode | Conclusion + demande de devis | V10: blog-actus/nettoyage-de-vitres-en-hauteur-perche-a-eau-pure-ou-nacelle | W10: ="https://www.nettoyage-vitres-bayonne.fr/"&V10 | X10: blog-actus, contact-devis | Y10: Rédigée | AC10: Page générée le 27/09/2026 — à mettre en ligne
A11: 10 | B11: 46293 | C11: Lundi | D11: S01 | E11: Article | F11: Articles | G11: B2B | H11: Article vitres en hauteur / immeubles | L11: Vitres en hauteur | M11: nettoyage vitres en hauteur | O11: Comment on lave des vitres à 13 m sans nacelle | P11: Comment on lave des vitres à 13 m sans nacelle — les conseils de ProVitres-64, laveur de vitres professionnel au Pays Basque et dans le Sud Landes. | Q11: Comment on lave des vitres à 13 m sans nacelle | R11: Introduction | Le problème | Les solutions | Notre méthode | Conclusion + demande de devis | V11: blog-actus/comment-on-lave-des-vitres-a-13-m-sans-nacelle | W11: ="https://www.nettoyage-vitres-bayonne.fr/"&V11 | X11: blog-actus, contact-devis | Y11: Rédigée | AC11: Page générée le 27/09/2026 — à mettre en ligne
A12: 11 | B12: 46294 | C12: Mardi | D12: S01 | E12: Page hors menu | F12: 1 · Piliers B2B | G12: B2B | H12: Page pilier métier | L12: Écoles, collèges & crèches | M12: Nettoyage vitres école Pays Basque | N12: lavage vitres école Landes, laveur de vitres écoles,, nettoyeur de vitres professionnel | O12: Nettoyage vitres école Pays Basque & Sud Landes | P12: Nettoyage vitres école au Pays Basque et dans le Sud Landes pour votre établissement scolaire : lavage à l'eau pure, vitres en hauteur jusqu'à 13 m,… | Q12: Nettoyage vitres école au Pays Basque et dans le Sud Landes | R12: Pourquoi confier votre établissement scolaire à un laveur de vitres pro | Ce que nous nettoyons | Vitres en hauteur : perche à eau pure jusqu'à 13 m, nacelle si besoin | Fréquence et contrat d'entretien | Villes desservies | Devis gratuit | T12: Interventions pendant les vacances, verrières et préaux | V12: nettoyage-vitres-ecole-pays-basque | W12: ="https://www.nettoyage-vitres-bayonne.fr/"&V12 | X12: service-de-nettoyage-professionnels, contact-devis | Y12: Rédigée | AC12: Page générée le 27/09/2026 — à mettre en ligne
A13: 12 | B13: 46294 | C13: Mardi | D13: S01 | E13: Page hors menu | F13: 1 · Piliers B2B | G13: B2B | H13: Page pilier métier | L13: Agences immobilières | M13: Nettoyage vitres agence immobilière Pays Basque | N13: lavage vitres agence immobilière Landes, laveur de vitres agences, nettoyeur de vitres professionnel | O13: Nettoyage vitres agence immobilière Pays Basque & Sud Landes | P13: Nettoyage vitres agence immobilière au Pays Basque et dans le Sud Landes pour votre agence immobilière : lavage à l'eau pure, vitres en hauteur jusqu'à 13… | Q13: Nettoyage vitres agence immobilière au Pays Basque et dans le Sud Landes | R13: Pourquoi confier votre agence immobilière à un laveur de vitres pro | Ce que nous nettoyons | Vitres en hauteur : perche à eau pure jusqu'à 13 m, nacelle si besoin | Fréquence et contrat d'entretien | Villes desservies | Devis gratuit | T13: Vitres propres avant photos et visites, tarif partenaire | V13: nettoyage-vitres-agence-immobiliere-pays-basque | W13: ="https://www.nettoyage-vitres-bayonne.fr/"&V13 | X13: service-de-nettoyage-professionnels, contact-devis | Y13: Rédigée | AC13: Page générée le 27/09/2026 — à mettre en ligne
A14: 13 | B14: 46294 | C14: Mardi | D14: S01 | E14: Page hors menu | F14: 1 · Piliers B2B | G14: B2B | H14: Page pilier métier | L14: Cabinets médicaux & paramédicaux | M14: Nettoyage vitres cabinet médical Pays Basque | N14: lavage vitres cabinet médical Landes, laveur de vitres cabinets, nettoyeur de vitres professionnel | O14: Nettoyage vitres cabinet médical Pays Basque & Sud Landes | P14: Nettoyage vitres cabinet médical au Pays Basque et dans le Sud Landes pour votre cabinet : lavage à l'eau pure, vitres en hauteur jusqu'à 13 m, contrat… | Q14: Nettoyage vitres cabinet médical au Pays Basque et dans le Sud Landes | R14: Pourquoi confier votre cabinet à un laveur de vitres pro | Ce que nous nettoyons | Vitres en hauteur : perche à eau pure jusqu'à 13 m, nacelle si besoin | Fréquence et contrat d'entretien | Villes desservies | Devis gratuit | T14: Interventions hors consultations, image d'hygiène | V14: nettoyage-vitres-cabinet-medical-pays-basque | W14: ="https://www.nettoyage-vitres-bayonne.fr/"&V14 | X14: service-de-nettoyage-professionnels, contact-devis | Y14: Rédigée | AC14: Page générée le 27/09/2026 — à mettre en ligne
A15: 14 | B15: 46294 | C15: Mardi | D15: S01 | E15: Page hors menu | F15: 1 · Piliers B2B | G15: B2B | H15: Page pilier métier | L15: Fin de chantier | M15: Nettoyage vitres fin de chantier Pays Basque | N15: lavage vitres fin de chantier Landes, laveur de vitres fin, nettoyeur de vitres professionnel | O15: Nettoyage vitres fin de chantier Pays Basque & Sud Landes | P15: Nettoyage vitres fin de chantier au Pays Basque et dans le Sud Landes pour votre chantier : lavage à l'eau pure, vitres en hauteur jusqu'à 13 m, contrat… | Q15: Nettoyage vitres fin de chantier au Pays Basque et dans le Sud Landes | R15: Pourquoi confier votre chantier à un laveur de vitres pro | Ce que nous nettoyons | Vitres en hauteur : perche à eau pure jusqu'à 13 m, nacelle si besoin | Fréquence et contrat d'entretien | Villes desservies | Devis gratuit | T15: Ciment, peinture, silicone : décapage sans rayer | V15: nettoyage-vitres-fin-de-chantier-pays-basque | W15: ="https://www.nettoyage-vitres-bayonne.fr/"&V15 | X15: service-de-nettoyage-professionnels, contact-devis | Y15: Rédigée | AC15: Page générée le 27/09/2026 — à mettre en ligne
A16: 15 | B16: 46294 | C16: Mardi | D16: S01 | E16: Page hors menu | F16: 1 · Piliers B2B | G16: B2B | H16: Page pilier métier | L16: Supermarchés & grandes surfaces | M16: Nettoyage vitres supermarché Pays Basque | N16: lavage vitres supermarché Landes, laveur de vitres supermarchés, nettoyeur de vitres professionnel | O16: Nettoyage vitres supermarché Pays Basque & Sud Landes | P16: Nettoyage vitres supermarché au Pays Basque et dans le Sud Landes pour votre magasin : lavage à l'eau pure, vitres en hauteur jusqu'à 13 m, contrat sur… | Q16: Nettoyage vitres supermarché au Pays Basque et dans le Sud Landes | R16: Pourquoi confier votre magasin à un laveur de vitres pro | Ce que nous nettoyons | Vitres en hauteur : perche à eau pure jusqu'à 13 m, nacelle si besoin | Fréquence et contrat d'entretien | Villes desservies | Devis gratuit | T16: Grandes façades vitrées, interventions avant l'ouverture | V16: nettoyage-vitres-supermarche-pays-basque | W16: ="https://www.nettoyage-vitres-bayonne.fr/"&V16 | X16: service-de-nettoyage-professionnels, contact-devis | Y16: Rédigée | AC16: Page générée le 27/09/2026 — à mettre en ligne
A17: 16 | B17: 46294 | C17: Mardi | D17: S01 | E17: Page hors menu | F17: 1 · Piliers B2B | G17: B2B | H17: Page pilier métier | L17: EHPAD, cliniques & résidences seniors | M17: Nettoyage vitres EHPAD Pays Basque | N17: lavage vitres ehpad Landes, laveur de vitres ehpad,, nettoyeur de vitres professionnel | O17: Nettoyage vitres EHPAD Pays Basque & Sud Landes | P17: Nettoyage vitres EHPAD au Pays Basque et dans le Sud Landes pour votre établissement : lavage à l'eau pure, vitres en hauteur jusqu'à 13 m, contrat sur… | Q17: Nettoyage vitres EHPAD au Pays Basque et dans le Sud Landes | R17: Pourquoi confier votre établissement à un laveur de vitres pro | Ce que nous nettoyons | Vitres en hauteur : perche à eau pure jusqu'à 13 m, nacelle si besoin | Fréquence et contrat d'entretien | Villes desservies | Devis gratuit | T17: Interventions discrètes, sans produit chimique (eau pure) | V17: nettoyage-vitres-ehpad-pays-basque | W17: ="https://www.nettoyage-vitres-bayonne.fr/"&V17 | X17: service-de-nettoyage-professionnels, contact-devis | Y17: Rédigée | AC17: Page générée le 27/09/2026 — à mettre en ligne
A18: 17 | B18: 46294 | C18: Mardi | D18: S01 | E18: Page hors menu | F18: 1 · Piliers B2B | G18: B2B | H18: Page pilier métier | L18: Campings & résidences de tourisme | M18: Nettoyage vitres camping Pays Basque | N18: lavage vitres camping Landes, laveur de vitres campings, nettoyeur de vitres professionnel | O18: Nettoyage vitres camping Pays Basque & Sud Landes | P18: Nettoyage vitres camping au Pays Basque et dans le Sud Landes pour votre camping : lavage à l'eau pure, vitres en hauteur jusqu'à 13 m, contrat sur… | Q18: Nettoyage vitres camping au Pays Basque et dans le Sud Landes | R18: Pourquoi confier votre camping à un laveur de vitres pro | Ce que nous nettoyons | Vitres en hauteur : perche à eau pure jusqu'à 13 m, nacelle si besoin | Fréquence et contrat d'entretien | Villes desservies | Devis gratuit | T18: Grand nettoyage avant l'ouverture de la saison | V18: nettoyage-vitres-camping-pays-basque | W18: ="https://www.nettoyage-vitres-bayonne.fr/"&V18 | X18: service-de-nettoyage-professionnels, contact-devis | Y18: Rédigée | AC18: Page générée le 27/09/2026 — à mettre en ligne
A19: 18 | B19: 46294 | C19: Mardi | D19: S01 | E19: Page hors menu | F19: 1 · Piliers B2B | G19: B2B | H19: Page pilier métier | L19: Notaires, avocats & professions libérales | M19: Nettoyage vitres cabinet notaire Pays Basque | N19: lavage vitres cabinet notaire Landes, laveur de vitres notaires,, nettoyeur de vitres professionnel | O19: Nettoyage vitres cabinet notaire Pays Basque & Sud Landes | P19: Nettoyage vitres cabinet notaire au Pays Basque et dans le Sud Landes pour votre cabinet : lavage à l'eau pure, vitres en hauteur jusqu'à 13 m, contrat… | Q19: Nettoyage vitres cabinet notaire au Pays Basque et dans le Sud Landes | R19: Pourquoi confier votre cabinet à un laveur de vitres pro | Ce que nous nettoyons | Vitres en hauteur : perche à eau pure jusqu'à 13 m, nacelle si besoin | Fréquence et contrat d'entretien | Villes desservies | Devis gratuit | T19: Image soignée, interventions hors rendez-vous | V19: nettoyage-vitres-cabinet-notaire-pays-basque | W19: ="https://www.nettoyage-vitres-bayonne.fr/"&V19 | X19: service-de-nettoyage-professionnels, contact-devis | Y19: Rédigée | AC19: Page générée le 27/09/2026 — à mettre en ligne
A20: 19 | B20: 46294 | C20: Mardi | D20: S01 | E20: Article | F20: Articles | G20: B2B | H20: Article vitres en hauteur / immeubles | L20: Vitres en hauteur | M20: nettoyage vitres en hauteur | O20: Immeubles de la côte basque : l'entretien des vitres en | P20: Immeubles de la côte basque : l'entretien des vitres en façade — les conseils de ProVitres-64, laveur de vitres professionnel au Pays Basque et dans le… | Q20: Immeubles de la côte basque : l'entretien des vitres en façade | R20: Introduction | Le problème | Les solutions | Notre méthode | Conclusion + demande de devis | V20: blog-actus/immeubles-de-la-cote-basque-l-entretien-des-vitres-en-facade | W20: ="https://www.nettoyage-vitres-bayonne.fr/"&V20 | X20: blog-actus, contact-devis | Y20: Rédigée | AC20: Page générée le 27/09/2026 — à mettre en ligne
A21: 20 | B21: 46294 | C21: Mardi | D21: S01 | E21: Article | F21: Articles | G21: B2B | H21: Article vitres en hauteur / immeubles | L21: Vitres en hauteur | M21: nettoyage vitres en hauteur | O21: Vitres d'immeuble : qui paie, le syndic ou les | P21: Vitres d'immeuble : qui paie, le syndic ou les copropriétaires ? — les conseils de ProVitres-64, laveur de vitres professionnel au Pays Basque et dans le… | Q21: Vitres d'immeuble : qui paie, le syndic ou les copropriétaires ? | R21: Introduction | Le problème | Les solutions | Notre méthode | Conclusion + demande de devis | V21: blog-actus/vitres-d-immeuble-qui-paie-le-syndic-ou-les-coproprietaires | W21: ="https://www.nettoyage-vitres-bayonne.fr/"&V21 | X21: blog-actus, contact-devis | Y21: Rédigée | AC21: Page générée le 27/09/2026 — à mettre en ligne
A22: 21 | B22: 46295 | C22: Mercredi | D22: S01 | E22: Page hors menu | F22: 1 · Piliers B2B | G22: B2B | H22: Page pilier métier | L22: Pharmacies | M22: Nettoyage vitrine pharmacie Pays Basque | N22: lavage vitrine pharmacie Landes, laveur de vitres pharmacies, nettoyeur de vitres professionnel | O22: Nettoyage vitrine pharmacie Pays Basque & Sud Landes | P22: Nettoyage vitrine pharmacie au Pays Basque et dans le Sud Landes pour votre pharmacie : lavage à l'eau pure, vitres en hauteur jusqu'à 13 m, contrat sur… | Q22: Nettoyage vitrine pharmacie au Pays Basque et dans le Sud Landes | R22: Pourquoi confier votre pharmacie à un laveur de vitres pro | Ce que nous nettoyons | Vitres en hauteur : perche à eau pure jusqu'à 13 m, nacelle si besoin | Fréquence et contrat d'entretien | Villes desservies | Devis gratuit | T22: Vitrine et croix visibles, passage avant l'ouverture | V22: nettoyage-vitrine-pharmacie-pays-basque | W22: ="https://www.nettoyage-vitres-bayonne.fr/"&V22 | X22: service-de-nettoyage-professionnels, contact-devis | Y22: Rédigée | AC22: Page générée le 27/09/2026 — à mettre en ligne
A23: 22 | B23: 46295 | C23: Mercredi | D23: S01 | E23: Page hors menu | F23: 1 · Piliers B2B | G23: B2B | H23: Page pilier métier | L23: Banques & assurances | M23: Nettoyage vitres agence bancaire Pays Basque | N23: lavage vitres agence bancaire Landes, laveur de vitres banques, nettoyeur de vitres professionnel | O23: Nettoyage vitres agence bancaire Pays Basque & Sud Landes | P23: Nettoyage vitres agence bancaire au Pays Basque et dans le Sud Landes pour votre agence : lavage à l'eau pure, vitres en hauteur jusqu'à 13 m, contrat sur… | Q23: Nettoyage vitres agence bancaire au Pays Basque et dans le Sud Landes | R23: Pourquoi confier votre agence à un laveur de vitres pro | Ce que nous nettoyons | Vitres en hauteur : perche à eau pure jusqu'à 13 m, nacelle si besoin | Fréquence et contrat d'entretien | Villes desservies | Devis gratuit | T23: Contrat multi-agences | V23: nettoyage-vitres-agence-bancaire-pays-basque | W23: ="https://www.nettoyage-vitres-bayonne.fr/"&V23 | X23: service-de-nettoyage-professionnels, contact-devis | Y23: Rédigée | AC23: Page générée le 27/09/2026 — à mettre en ligne
A24: 23 | B24: 46295 | C24: Mercredi | D24: S01 | E24: Page hors menu | F24: 1 · Piliers B2B | G24: B2B | H24: Page pilier métier | L24: Concessions & loueurs de voitures | M24: Nettoyage vitres concession automobile Pays Basque | N24: lavage vitres concession automobile Landes, laveur de vitres concessions, nettoyeur de vitres professionnel | O24: Nettoyage vitres concession automobile Pays Basque & Sud Landes | P24: Nettoyage vitres concession automobile au Pays Basque et dans le Sud Landes pour votre showroom : lavage à l'eau pure, vitres en hauteur jusqu'à 13 m,… | Q24: Nettoyage vitres concession automobile au Pays Basque et dans le Sud Landes | R24: Pourquoi confier votre showroom à un laveur de vitres pro | Ce que nous nettoyons | Vitres en hauteur : perche à eau pure jusqu'à 13 m, nacelle si besoin | Fréquence et contrat d'entretien | Villes desservies | Devis gratuit | T24: Grands showrooms vitrés, façades hautes | V24: nettoyage-vitres-concession-automobile-pays-basque | W24: ="https://www.nettoyage-vitres-bayonne.fr/"&V24 | X24: service-de-nettoyage-professionnels, contact-devis | Y24: Rédigée | AC24: Page générée le 27/09/2026 — à mettre en ligne
A25: 24 | B25: 46295 | C25: Mercredi | D25: S01 | E25: Page hors menu | F25: 1 · Piliers B2B | G25: B2B | H25: Page pilier métier | L25: Salles de sport & loisirs | M25: Nettoyage vitres salle de sport Pays Basque | N25: lavage vitres salle de sport Landes, laveur de vitres salles, nettoyeur de vitres professionnel | O25: Nettoyage vitres salle de sport Pays Basque & Sud Landes | P25: Nettoyage vitres salle de sport au Pays Basque et dans le Sud Landes pour votre salle : lavage à l'eau pure, vitres en hauteur jusqu'à 13 m, contrat sur… | Q25: Nettoyage vitres salle de sport au Pays Basque et dans le Sud Landes | R25: Pourquoi confier votre salle à un laveur de vitres pro | Ce que nous nettoyons | Vitres en hauteur : perche à eau pure jusqu'à 13 m, nacelle si besoin | Fréquence et contrat d'entretien | Villes desservies | Devis gratuit | T25: Baies et miroirs sans traces | V25: nettoyage-vitres-salle-de-sport-pays-basque | W25: ="https://www.nettoyage-vitres-bayonne.fr/"&V25 | X25: service-de-nettoyage-professionnels, contact-devis | Y25: Rédigée | AC25: Page générée le 27/09/2026 — à mettre en ligne
A26: 25 | B26: 46295 | C26: Mercredi | D26: S01 | E26: Page hors menu | F26: 1 · Piliers B2B | G26: B2B | H26: Page pilier métier | L26: Instituts & salons de coiffure | M26: Nettoyage vitrine salon de coiffure Pays Basque | N26: lavage vitrine salon de coiffure Landes, laveur de vitres instituts, nettoyeur de vitres professionnel | O26: Nettoyage vitrine salon de coiffure Pays Basque & Sud Landes | P26: Nettoyage vitrine salon de coiffure au Pays Basque et dans le Sud Landes pour votre salon : lavage à l'eau pure, vitres en hauteur jusqu'à 13 m, contrat… | Q26: Nettoyage vitrine salon de coiffure au Pays Basque et dans le Sud Landes | R26: Pourquoi confier votre salon à un laveur de vitres pro | Ce que nous nettoyons | Vitres en hauteur : perche à eau pure jusqu'à 13 m, nacelle si besoin | Fréquence et contrat d'entretien | Villes desservies | Devis gratuit | T26: Vitrine et miroirs impeccables | V26: nettoyage-vitrine-salon-coiffure-pays-basque | W26: ="https://www.nettoyage-vitres-bayonne.fr/"&V26 | X26: service-de-nettoyage-professionnels, contact-devis | Y26: Rédigée | AC26: Page générée le 27/09/2026 — à mettre en ligne
A27: 26 | B27: 46295 | C27: Mercredi | D27: S01 | E27: Page hors menu | F27: 1 · Piliers B2B | G27: B2B | H27: Page pilier métier | L27: Locaux industriels & entrepôts | M27: Nettoyage vitres locaux industriels Pays Basque | N27: lavage vitres locaux industriels Landes, laveur de vitres locaux, nettoyeur de vitres professionnel | O27: Nettoyage vitres locaux industriels Pays Basque & Sud Landes | P27: Nettoyage vitres locaux industriels au Pays Basque et dans le Sud Landes pour vos locaux : lavage à l'eau pure, vitres en hauteur jusqu'à 13 m, contrat… | Q27: Nettoyage vitres locaux industriels au Pays Basque et dans le Sud Landes | R27: Pourquoi confier vos locaux à un laveur de vitres pro | Ce que nous nettoyons | Vitres en hauteur : perche à eau pure jusqu'à 13 m, nacelle si besoin | Fréquence et contrat d'entretien | Villes desservies | Devis gratuit | T27: Vitrages en hauteur, bardages translucides, sheds | V27: nettoyage-vitres-locaux-industriels-pays-basque | W27: ="https://www.nettoyage-vitres-bayonne.fr/"&V27 | X27: service-de-nettoyage-professionnels, contact-devis | Y27: Rédigée | AC27: Page générée le 27/09/2026 — à mettre en ligne
A28: 27 | B28: 46295 | C28: Mercredi | D28: S01 | E28: Page hors menu | F28: 1 · Piliers B2B | G28: B2B | H28: Page pilier métier | L28: Abribus, gares & transports | M28: Nettoyage abribus Pays Basque | N28: lavage abribus Landes, laveur de vitres abribus,, nettoyeur de vitres professionnel | O28: Nettoyage abribus Pays Basque & Sud Landes | ProVitres-64 | P28: Nettoyage abribus au Pays Basque et dans le Sud Landes pour vos abribus et gares : lavage à l'eau pure, vitres en hauteur jusqu'à 13 m, contrat sur… | Q28: Nettoyage abribus au Pays Basque et dans le Sud Landes | R28: Pourquoi confier vos abribus et gares à un laveur de vitres pro | Ce que nous nettoyons | Vitres en hauteur : perche à eau pure jusqu'à 13 m, nacelle si besoin | Fréquence et contrat d'entretien | Villes desservies | Devis gratuit | T28: Tournées planifiées, vitres anti-graffiti | V28: nettoyage-abribus-pays-basque | W28: ="https://www.nettoyage-vitres-bayonne.fr/"&V28 | X28: service-de-nettoyage-professionnels, contact-devis | Y28: Rédigée | AC28: Page générée le 27/09/2026 — à mettre en ligne
A29: 28 | B29: 46295 | C29: Mercredi | D29: S01 | E29: Page hors menu | F29: 1 · Piliers B2B | G29: B2B | H29: Page pilier métier | L29: Ports & capitaineries | M29: Nettoyage vitres port Pays Basque | N29: lavage vitres port Landes, laveur de vitres ports, nettoyeur de vitres professionnel | O29: Nettoyage vitres port Pays Basque & Sud Landes | P29: Nettoyage vitres port au Pays Basque et dans le Sud Landes pour vos locaux portuaires : lavage à l'eau pure, vitres en hauteur jusqu'à 13 m, contrat sur… | Q29: Nettoyage vitres port au Pays Basque et dans le Sud Landes | R29: Pourquoi confier vos locaux portuaires à un laveur de vitres pro | Ce que nous nettoyons | Vitres en hauteur : perche à eau pure jusqu'à 13 m, nacelle si besoin | Fréquence et contrat d'entretien | Villes desservies | Devis gratuit | T29: Sel et embruns : vitres de capitaineries, commerces du port | V29: nettoyage-vitres-port-pays-basque | W29: ="https://www.nettoyage-vitres-bayonne.fr/"&V29 | X29: service-de-nettoyage-professionnels, contact-devis | Y29: Rédigée | AC29: Page générée le 27/09/2026 — à mettre en ligne
A30: 29 | B30: 46295 | C30: Mercredi | D30: S01 | E30: Article | F30: Articles | G30: B2B | H30: Article vitres en hauteur / immeubles | L30: Vitres en hauteur | M30: nettoyage vitres en hauteur | O30: Travail en hauteur : les règles de sécurité d'un laveur de | P30: Travail en hauteur : les règles de sécurité d'un laveur de vitres — les conseils de ProVitres-64, laveur de vitres professionnel au Pays Basque et dans le… | Q30: Travail en hauteur : les règles de sécurité d'un laveur de vitres | R30: Introduction | Le problème | Les solutions | Notre méthode | Conclusion + demande de devis | V30: blog-actus/travail-en-hauteur-les-regles-de-securite-d-un-laveur-de-vitres | W30: ="https://www.nettoyage-vitres-bayonne.fr/"&V30 | X30: blog-actus, contact-devis | Y30: Rédigée | AC30: Page générée le 27/09/2026 — à mettre en ligne
A31: 30 | B31: 46295 | C31: Mercredi | D31: S01 | E31: Article | F31: Articles | G31: B2B | H31: Article vitres en hauteur / immeubles | L31: Vitres en hauteur | M31: nettoyage vitres en hauteur | O31: Façades vitrées : les entretenir sans échafaudage | P31: Façades vitrées : les entretenir sans échafaudage — les conseils de ProVitres-64, laveur de vitres professionnel au Pays Basque et dans le Sud Landes. | Q31: Façades vitrées : les entretenir sans échafaudage | R31: Introduction | Le problème | Les solutions | Notre méthode | Conclusion + demande de devis | V31: blog-actus/facades-vitrees-les-entretenir-sans-echafaudage | W31: ="https://www.nettoyage-vitres-bayonne.fr/"&V31 | X31: blog-actus, contact-devis | Y31: Rédigée | AC31: Page générée le 27/09/2026 — à mettre en ligne
A32: 31 | B32: 46296 | C32: Jeudi | D32: S01 | E32: Page hors menu | F32: 1 · Piliers B2B | G32: B2B | H32: Page pilier service | L32: Service | M32: Entreprise de nettoyage de vitres | N32: société nettoyage vitres, prestataire vitres, laveur de vitres professionnel | O32: Entreprise de nettoyage de vitres | ProVitres-64 | P32: Entreprise de nettoyage de vitres par ProVitres-64, laveur de vitres professionnel basé à Boucau : eau pure, perche 13 m, nacelle. Pays Basque et Sud… | Q32: Entreprise de nettoyage de vitres — ProVitres-64 | R32: Notre prestation | Pour qui ? | Vitres en hauteur : perche à eau pure jusqu'à 13 m, nacelle si besoin | Sécurité & travail en hauteur | Zones d'intervention | Devis gratuit | T32: Vitres en hauteur : perche à eau pure jusqu'à 13 m, nacelle si besoin | V32: entreprise-nettoyage-vitres-pays-basque | W32: ="https://www.nettoyage-vitres-bayonne.fr/"&V32 | X32: service-de-nettoyage-professionnels, contact-devis | Y32: Rédigée | AC32: Page générée le 27/09/2026 — à mettre en ligne
A33: 32 | B33: 46296 | C33: Jeudi | D33: S01 | E33: Page hors menu | F33: 1 · Piliers B2B | G33: B2B | H33: Page pilier service | L33: Service | M33: Nettoyage vitres en hauteur | N33: vitres difficiles d'accès, perche télescopique 13 m, sans nacelle, lavage vitres hauteur | O33: Nettoyage vitres en hauteur | ProVitres-64 | P33: Nettoyage vitres en hauteur par ProVitres-64, laveur de vitres professionnel basé à Boucau : eau pure, perche 13 m, nacelle. Pays Basque et Sud Landes.… | Q33: Nettoyage vitres en hauteur — ProVitres-64 | R33: Notre prestation | Pour qui ? | Vitres en hauteur : perche à eau pure jusqu'à 13 m, nacelle si besoin | Sécurité & travail en hauteur | Zones d'intervention | Devis gratuit | T33: Vitres en hauteur : perche à eau pure jusqu'à 13 m, nacelle si besoin | V33: nettoyage-vitres-hauteur-eau-pure | W33: ="https://www.nettoyage-vitres-bayonne.fr/"&V33 | X33: service-de-nettoyage-professionnels, contact-devis | Y33: Rédigée | AC33: Page générée le 27/09/2026 — à mettre en ligne
A34: 33 | B34: 46296 | C34: Jeudi | D34: S01 | E34: Page hors menu | F34: 1 · Piliers B2B | G34: B2B | H34: Page pilier service | L34: Service | M34: Nettoyage vitres par nacelle | N34: nacelle, travail en hauteur, vitres grande hauteur | O34: Nettoyage vitres par nacelle | ProVitres-64 | P34: Nettoyage vitres par nacelle par ProVitres-64, laveur de vitres professionnel basé à Boucau : eau pure, perche 13 m, nacelle. Pays Basque et Sud Landes.… | Q34: Nettoyage vitres par nacelle — ProVitres-64 | R34: Notre prestation | Pour qui ? | Vitres en hauteur : perche à eau pure jusqu'à 13 m, nacelle si besoin | Sécurité & travail en hauteur | Zones d'intervention | Devis gratuit | T34: Vitres en hauteur : perche à eau pure jusqu'à 13 m, nacelle si besoin | V34: nettoyage-vitres-nacelle-pays-basque | W34: ="https://www.nettoyage-vitres-bayonne.fr/"&V34 | X34: service-de-nettoyage-professionnels, contact-devis | Y34: Rédigée | AC34: Page générée le 27/09/2026 — à mettre en ligne
A35: 34 | B35: 46296 | C35: Jeudi | D35: S01 | E35: Page hors menu | F35: 1 · Piliers B2B | G35: B2B | H35: Page pilier service | L35: Service | M35: Nettoyage façade vitrée | N35: façade verre, mur rideau, vitrage extérieur immeuble | O35: Nettoyage façade vitrée | ProVitres-64 | P35: Nettoyage façade vitrée par ProVitres-64, laveur de vitres professionnel basé à Boucau : eau pure, perche 13 m, nacelle. Pays Basque et Sud Landes. Devis… | Q35: Nettoyage façade vitrée — ProVitres-64 | R35: Notre prestation | Pour qui ? | Vitres en hauteur : perche à eau pure jusqu'à 13 m, nacelle si besoin | Sécurité & travail en hauteur | Zones d'intervention | Devis gratuit | T35: Vitres en hauteur : perche à eau pure jusqu'à 13 m, nacelle si besoin | V35: nettoyage-facade-vitree-pays-basque | W35: ="https://www.nettoyage-vitres-bayonne.fr/"&V35 | X35: service-de-nettoyage-professionnels, contact-devis | Y35: Rédigée | AC35: Page générée le 27/09/2026 — à mettre en ligne
A36: 35 | B36: 46296 | C36: Jeudi | D36: S01 | E36: Page hors menu | F36: 1 · Piliers B2B | G36: B2B | H36: Page pilier service | L36: Service | M36: Nettoyage verrière et puits de lumière | N36: verrière toit, puits de lumière, verrière atelier | O36: Nettoyage verrière et puits de lumière | ProVitres-64 | P36: Nettoyage verrière et puits de lumière par ProVitres-64, laveur de vitres professionnel basé à Boucau : eau pure, perche 13 m, nacelle. Pays Basque et Sud… | Q36: Nettoyage verrière et puits de lumière — ProVitres-64 | R36: Notre prestation | Pour qui ? | Vitres en hauteur : perche à eau pure jusqu'à 13 m, nacelle si besoin | Sécurité & travail en hauteur | Zones d'intervention | Devis gratuit | T36: Vitres en hauteur : perche à eau pure jusqu'à 13 m, nacelle si besoin | V36: nettoyage-verriere-pays-basque | W36: ="https://www.nettoyage-vitres-bayonne.fr/"&V36 | X36: service-de-nettoyage-professionnels, contact-devis | Y36: Rédigée | AC36: Page générée le 27/09/2026 — à mettre en ligne
A37: 36 | B37: 46296 | C37: Jeudi | D37: S01 | E37: Page hors menu | F37: 1 · Piliers B2B | G37: B2B | H37: Page pilier service | L37: Service | M37: Nettoyage vitres bâtiments publics | N37: collectivités, marchés publics, Chorus Pro, communes | O37: Nettoyage vitres bâtiments publics | ProVitres-64 | P37: Nettoyage vitres bâtiments publics par ProVitres-64, laveur de vitres professionnel basé à Boucau : eau pure, perche 13 m, nacelle. Pays Basque et Sud… | Q37: Nettoyage vitres bâtiments publics — ProVitres-64 | R37: Notre prestation | Pour qui ? | Vitres en hauteur : perche à eau pure jusqu'à 13 m, nacelle si besoin | Sécurité & travail en hauteur | Zones d'intervention | Devis gratuit | T37: Vitres en hauteur : perche à eau pure jusqu'à 13 m, nacelle si besoin | V37: nettoyage-vitres-batiments-publics-pays-basque | W37: ="https://www.nettoyage-vitres-bayonne.fr/"&V37 | X37: service-de-nettoyage-professionnels, contact-devis | Y37: Rédigée | AC37: Page générée le 27/09/2026 — à mettre en ligne
A38: 37 | B38: 46296 | C38: Jeudi | D38: S01 | E38: Page hors menu | F38: 1 · Piliers B2B | G38: B2B | H38: Page pilier service | L38: Service | M38: Contrat entretien vitres entreprise | N38: contrat nettoyage vitres, entretien mensuel, prestataire vitres | O38: Contrat entretien vitres entreprise | ProVitres-64 | P38: Contrat entretien vitres entreprise par ProVitres-64, laveur de vitres professionnel basé à Boucau : eau pure, perche 13 m, nacelle. Pays Basque et Sud… | Q38: Contrat entretien vitres entreprise — ProVitres-64 | R38: Notre prestation | Pour qui ? | Vitres en hauteur : perche à eau pure jusqu'à 13 m, nacelle si besoin | Sécurité & travail en hauteur | Zones d'intervention | Devis gratuit | T38: Vitres en hauteur : perche à eau pure jusqu'à 13 m, nacelle si besoin | V38: contrat-entretien-vitres-entreprise-pays-basque | W38: ="https://www.nettoyage-vitres-bayonne.fr/"&V38 | X38: service-de-nettoyage-professionnels, contact-devis | Y38: Rédigée | AC38: Page générée le 27/09/2026 — à mettre en ligne
A39: 38 | B39: 46296 | C39: Jeudi | D39: S01 | E39: Page hors menu | F39: 1 · Piliers B2B | G39: B2B | H39: Page pilier service | L39: Service | M39: Nettoyage fenêtres professionnel | N39: lavage fenêtres, laveur de fenêtres, nettoyage carreaux | O39: Nettoyage fenêtres professionnel | ProVitres-64 | P39: Nettoyage fenêtres professionnel par ProVitres-64, laveur de vitres professionnel basé à Boucau : eau pure, perche 13 m, nacelle. Pays Basque et Sud… | Q39: Nettoyage fenêtres professionnel — ProVitres-64 | R39: Notre prestation | Pour qui ? | Vitres en hauteur : perche à eau pure jusqu'à 13 m, nacelle si besoin | Sécurité & travail en hauteur | Zones d'intervention | Devis gratuit | T39: Vitres en hauteur : perche à eau pure jusqu'à 13 m, nacelle si besoin | V39: nettoyage-fenetres-pays-basque | W39: ="https://www.nettoyage-vitres-bayonne.fr/"&V39 | X39: service-de-nettoyage-professionnels, contact-devis | Y39: Rédigée | AC39: Page générée le 27/09/2026 — à mettre en ligne
A40: 39 | B40: 46296 | C40: Jeudi | D40: S01 | E40: Article | F40: Articles | G40: B2B | H40: Article collectivités | L40: Mairies & collectivités | M40: nettoyage vitres mairie | O40: Nettoyage des vitres des bâtiments communaux : ce que doit | P40: Nettoyage des vitres des bâtiments communaux : ce que doit prévoir une mairie — les conseils de ProVitres-64, laveur de vitres professionnel au Pays… | Q40: Nettoyage des vitres des bâtiments communaux : ce que doit prévoir une mairie | R40: Introduction | Le problème | Les solutions | Notre méthode | Conclusion + demande de devis | V40: blog-actus/nettoyage-des-vitres-des-batiments-communaux-ce-que-doit-prevoir-une-mairie | W40: ="https://www.nettoyage-vitres-bayonne.fr/"&V40 | X40: blog-actus, contact-devis | Y40: Rédigée | AC40: Page générée le 27/09/2026 — à mettre en ligne
A41: 40 | B41: 46296 | C41: Jeudi | D41: S01 | E41: Article | F41: Articles | G41: B2B | H41: Article collectivités | L41: Mairies & collectivités | M41: nettoyage vitres mairie | O41: Marché public de nettoyage de vitres : comment le rédiger | P41: Marché public de nettoyage de vitres : comment le rédiger — les conseils de ProVitres-64, laveur de vitres professionnel au Pays Basque et dans le Sud Landes. | Q41: Marché public de nettoyage de vitres : comment le rédiger | R41: Introduction | Le problème | Les solutions | Notre méthode | Conclusion + demande de devis | V41: blog-actus/marche-public-de-nettoyage-de-vitres-comment-le-rediger | W41: ="https://www.nettoyage-vitres-bayonne.fr/"&V41 | X41: blog-actus, contact-devis | Y41: Rédigée | AC41: Page générée le 27/09/2026 — à mettre en ligne
A42: 41 | B42: 46297 | C42: Vendredi | D42: S01 | E42: Page hors menu | F42: 1 · Piliers B2B | G42: B2B | H42: Page pilier service | L42: Service | M42: Nettoyage vitrerie professionnelle | N42: entretien vitrerie, surfaces vitrées, vitrages | O42: Nettoyage vitrerie professionnelle | ProVitres-64 | P42: Nettoyage vitrerie professionnelle par ProVitres-64, laveur de vitres professionnel basé à Boucau : eau pure, perche 13 m, nacelle. Pays Basque et Sud… | Q42: Nettoyage vitrerie professionnelle — ProVitres-64 | R42: Notre prestation | Pour qui ? | Vitres en hauteur : perche à eau pure jusqu'à 13 m, nacelle si besoin | Sécurité & travail en hauteur | Zones d'intervention | Devis gratuit | T42: Vitres en hauteur : perche à eau pure jusqu'à 13 m, nacelle si besoin | V42: nettoyage-vitrerie-pays-basque | W42: ="https://www.nettoyage-vitres-bayonne.fr/"&V42 | X42: service-de-nettoyage-professionnels, contact-devis | Y42: Rédigée | AC42: Page générée le 27/09/2026 — à mettre en ligne
A43: 42 | B43: 46297 | C43: Vendredi | D43: S01 | E43: Page hors menu | F43: 1 · Piliers B2B | G43: B2B | H43: Page pilier service | L43: Service | M43: Nettoyage garde-corps en verre | N43: balustrade verre, rambarde vitrée, terrasse vitrée | O43: Nettoyage garde-corps en verre | ProVitres-64 | P43: Nettoyage garde-corps en verre par ProVitres-64, laveur de vitres professionnel basé à Boucau : eau pure, perche 13 m, nacelle. Pays Basque et Sud Landes.… | Q43: Nettoyage garde-corps en verre — ProVitres-64 | R43: Notre prestation | Pour qui ? | Vitres en hauteur : perche à eau pure jusqu'à 13 m, nacelle si besoin | Sécurité & travail en hauteur | Zones d'intervention | Devis gratuit | T43: Vitres en hauteur : perche à eau pure jusqu'à 13 m, nacelle si besoin | V43: nettoyage-garde-corps-verre-pays-basque | W43: ="https://www.nettoyage-vitres-bayonne.fr/"&V43 | X43: service-de-nettoyage-professionnels, contact-devis | Y43: Rédigée | AC43: Page générée le 27/09/2026 — à mettre en ligne
A44: 43 | B44: 46297 | C44: Vendredi | D44: S01 | E44: Page hors menu | F44: 1 · Piliers B2B | G44: B2B | H44: Page pilier service | L44: Service | M44: Nettoyage panneaux solaires professionnels | N44: panneaux photovoltaïques entreprise, rendement, toiture | O44: Nettoyage panneaux solaires professionnels | ProVitres-64 | P44: Nettoyage panneaux solaires professionnels par ProVitres-64, laveur de vitres professionnel basé à Boucau : eau pure, perche 13 m, nacelle. Pays Basque et… | Q44: Nettoyage panneaux solaires professionnels — ProVitres-64 | R44: Notre prestation | Pour qui ? | Vitres en hauteur : perche à eau pure jusqu'à 13 m, nacelle si besoin | Sécurité & travail en hauteur | Zones d'intervention | Devis gratuit | T44: Vitres en hauteur : perche à eau pure jusqu'à 13 m, nacelle si besoin | V44: nettoyage-panneaux-solaires-professionnels | W44: ="https://www.nettoyage-vitres-bayonne.fr/"&V44 | X44: service-de-nettoyage-professionnels, contact-devis | Y44: Rédigée | AC44: Page générée le 27/09/2026 — à mettre en ligne
A45: 44 | B45: 46297 | C45: Vendredi | D45: S01 | E45: Page hors menu | F45: 1 · Piliers B2B | G45: B2B | H45: Page pilier service | L45: Service | M45: Nettoyage panneaux solaires hangar agricole | N45: photovoltaïque agricole, hangar, bâtiment d'élevage | O45: Nettoyage panneaux solaires hangar agricole | ProVitres-64 | P45: Nettoyage panneaux solaires hangar agricole par ProVitres-64, laveur de vitres professionnel basé à Boucau : eau pure, perche 13 m, nacelle. Pays Basque… | Q45: Nettoyage panneaux solaires hangar agricole — ProVitres-64 | R45: Notre prestation | Pour qui ? | Vitres en hauteur : perche à eau pure jusqu'à 13 m, nacelle si besoin | Sécurité & travail en hauteur | Zones d'intervention | Devis gratuit | T45: Vitres en hauteur : perche à eau pure jusqu'à 13 m, nacelle si besoin | V45: nettoyage-panneaux-solaires-hangar-agricole | W45: ="https://www.nettoyage-vitres-bayonne.fr/"&V45 | X45: service-de-nettoyage-professionnels, contact-devis | Y45: Rédigée | AC45: Page générée le 27/09/2026 — à mettre en ligne
A46: 45 | B46: 46297 | C46: Vendredi | D46: S01 | E46: Page hors menu | F46: 1 · Piliers B2B | G46: B2B | H46: Page pilier service | L46: Service | M46: Nettoyage vitres aéroport et loueurs | N46: aéroport Biarritz Pays Basque, agences de location, halls vitrés | O46: Nettoyage vitres aéroport et loueurs | ProVitres-64 | P46: Nettoyage vitres aéroport et loueurs par ProVitres-64, laveur de vitres professionnel basé à Boucau : eau pure, perche 13 m, nacelle. Pays Basque et Sud… | Q46: Nettoyage vitres aéroport et loueurs — ProVitres-64 | R46: Notre prestation | Pour qui ? | Vitres en hauteur : perche à eau pure jusqu'à 13 m, nacelle si besoin | Sécurité & travail en hauteur | Zones d'intervention | Devis gratuit | T46: Vitres en hauteur : perche à eau pure jusqu'à 13 m, nacelle si besoin | V46: nettoyage-vitres-aeroport-biarritz | W46: ="https://www.nettoyage-vitres-bayonne.fr/"&V46 | X46: service-de-nettoyage-professionnels, contact-devis | Y46: Rédigée | AC46: Page générée le 27/09/2026 — à mettre en ligne
A47: 46 | B47: 46297 | C47: Vendredi | D47: S01 | E47: Page hors menu | F47: 1 · Piliers B2B | G47: B2B | H47: Page pilier service | L47: Service | M47: Laveur de vitres Côte basque | N47: Biarritz, Anglet, Saint-Jean-de-Luz, Hendaye, Bidart | O47: Laveur de vitres Côte basque | ProVitres-64 | P47: Laveur de vitres Côte basque par ProVitres-64, laveur de vitres professionnel basé à Boucau : eau pure, perche 13 m, nacelle. Pays Basque et Sud Landes.… | Q47: Laveur de vitres Côte basque — ProVitres-64 | R47: Notre prestation | Pour qui ? | Vitres en hauteur : perche à eau pure jusqu'à 13 m, nacelle si besoin | Sécurité & travail en hauteur | Zones d'intervention | Devis gratuit | T47: Vitres en hauteur : perche à eau pure jusqu'à 13 m, nacelle si besoin | V47: laveur-vitres-cote-basque | W47: ="https://www.nettoyage-vitres-bayonne.fr/"&V47 | X47: service-de-nettoyage-professionnels, contact-devis | Y47: Rédigée | AC47: Page générée le 27/09/2026 — à mettre en ligne
A48: 47 | B48: 46297 | C48: Vendredi | D48: S01 | E48: Page hors menu | F48: 1 · Piliers B2B | G48: B2B | H48: Page pilier service | L48: Service | M48: Laveur de vitres BAB | N48: Bayonne Anglet Biarritz, nettoyage vitres BAB | O48: Laveur de vitres BAB | ProVitres-64 | P48: Laveur de vitres BAB par ProVitres-64, laveur de vitres professionnel basé à Boucau : eau pure, perche 13 m, nacelle. Pays Basque et Sud Landes. Devis… | Q48: Laveur de vitres BAB — ProVitres-64 | R48: Notre prestation | Pour qui ? | Vitres en hauteur : perche à eau pure jusqu'à 13 m, nacelle si besoin | Sécurité & travail en hauteur | Zones d'intervention | Devis gratuit | T48: Vitres en hauteur : perche à eau pure jusqu'à 13 m, nacelle si besoin | V48: laveur-vitres-bab | W48: ="https://www.nettoyage-vitres-bayonne.fr/"&V48 | X48: service-de-nettoyage-professionnels, contact-devis | Y48: Rédigée | AC48: Page générée le 27/09/2026 — à mettre en ligne
A49: 48 | B49: 46297 | C49: Vendredi | D49: S01 | E49: Page hors menu | F49: 1 · Piliers B2B | G49: B2B | H49: Page pilier service | L49: Service | M49: Nettoyage vitres Sud Landes | N49: Capbreton, Hossegor, Seignosse, Dax, Tarnos, Labenne | O49: Nettoyage vitres Sud Landes | ProVitres-64 | P49: Nettoyage vitres Sud Landes par ProVitres-64, laveur de vitres professionnel basé à Boucau : eau pure, perche 13 m, nacelle. Pays Basque et Sud Landes.… | Q49: Nettoyage vitres Sud Landes — ProVitres-64 | R49: Notre prestation | Pour qui ? | Vitres en hauteur : perche à eau pure jusqu'à 13 m, nacelle si besoin | Sécurité & travail en hauteur | Zones d'intervention | Devis gratuit | T49: Vitres en hauteur : perche à eau pure jusqu'à 13 m, nacelle si besoin | V49: nettoyage-vitres-sud-landes | W49: ="https://www.nettoyage-vitres-bayonne.fr/"&V49 | X49: service-de-nettoyage-professionnels, contact-devis | Y49: Rédigée | AC49: Page générée le 27/09/2026 — à mettre en ligne
A50: 49 | B50: 46297 | C50: Vendredi | D50: S01 | E50: Article | F50: Articles | G50: B2B | H50: Article collectivités | L50: Mairies & collectivités | M50: nettoyage vitres mairie | O50: Écoles : quand nettoyer les vitres sans gêner les classes | P50: Écoles : quand nettoyer les vitres sans gêner les classes — les conseils de ProVitres-64, laveur de vitres professionnel au Pays Basque et dans le Sud Landes. | Q50: Écoles : quand nettoyer les vitres sans gêner les classes | R50: Introduction | Le problème | Les solutions | Notre méthode | Conclusion + demande de devis | V50: blog-actus/ecoles-quand-nettoyer-les-vitres-sans-gener-les-classes | W50: ="https://www.nettoyage-vitres-bayonne.fr/"&V50 | X50: blog-actus, contact-devis | Y50: Rédigée | AC50: Page générée le 27/09/2026 — à mettre en ligne
A51: 50 | B51: 46297 | C51: Vendredi | D51: S01 | E51: Article | F51: Articles | G51: B2B | H51: Article collectivités | L51: Mairies & collectivités | M51: nettoyage vitres mairie | O51: Chorus Pro : la facturation d'un laveur de vitres aux | P51: Chorus Pro : la facturation d'un laveur de vitres aux collectivités — les conseils de ProVitres-64, laveur de vitres professionnel au Pays Basque et dans… | Q51: Chorus Pro : la facturation d'un laveur de vitres aux collectivités | R51: Introduction | Le problème | Les solutions | Notre méthode | Conclusion + demande de devis | V51: blog-actus/chorus-pro-la-facturation-d-un-laveur-de-vitres-aux-collectivites | W51: ="https://www.nettoyage-vitres-bayonne.fr/"&V51 | X51: blog-actus, contact-devis | Y51: Rédigée | AC51: Page générée le 27/09/2026 — à mettre en ligne
A52: 51 | B52: 46298 | C52: Samedi | D52: S01 | E52: Page hors menu | F52: 1 · Piliers B2B | G52: B2B | H52: Page pilier service | L52: Service | M52: Lavage vitres Landes | N52: laveur vitres Landes 40, nettoyage vitres 40 | O52: Lavage vitres Landes | ProVitres-64 | P52: Lavage vitres Landes par ProVitres-64, laveur de vitres professionnel basé à Boucau : eau pure, perche 13 m, nacelle. Pays Basque et Sud Landes. Devis… | Q52: Lavage vitres Landes — ProVitres-64 | R52: Notre prestation | Pour qui ? | Vitres en hauteur : perche à eau pure jusqu'à 13 m, nacelle si besoin | Sécurité & travail en hauteur | Zones d'intervention | Devis gratuit | T52: Vitres en hauteur : perche à eau pure jusqu'à 13 m, nacelle si besoin | V52: lavage-vitres-landes | W52: ="https://www.nettoyage-vitres-bayonne.fr/"&V52 | X52: service-de-nettoyage-professionnels, contact-devis | Y52: Rédigée | AC52: Page générée le 27/09/2026 — à mettre en ligne
A53: 52 | B53: 46298 | C53: Samedi | D53: S01 | E53: Page hors menu | F53: 1 · Piliers B2B | G53: B2B | H53: Page pilier service | L53: Service | M53: Nettoyeur de vitres Pyrénées-Atlantiques | N53: laveur vitres 64, nettoyage vitres 64 | O53: Nettoyeur de vitres Pyrénées-Atlantiques | ProVitres-64 | P53: Nettoyeur de vitres Pyrénées-Atlantiques par ProVitres-64, laveur de vitres professionnel basé à Boucau : eau pure, perche 13 m, nacelle. Pays Basque et… | Q53: Nettoyeur de vitres Pyrénées-Atlantiques — ProVitres-64 | R53: Notre prestation | Pour qui ? | Vitres en hauteur : perche à eau pure jusqu'à 13 m, nacelle si besoin | Sécurité & travail en hauteur | Zones d'intervention | Devis gratuit | T53: Vitres en hauteur : perche à eau pure jusqu'à 13 m, nacelle si besoin | V53: nettoyeur-vitres-pyrenees-atlantiques | W53: ="https://www.nettoyage-vitres-bayonne.fr/"&V53 | X53: service-de-nettoyage-professionnels, contact-devis | Y53: Rédigée | AC53: Page générée le 27/09/2026 — à mettre en ligne
A54: 53 | B54: 46298 | C54: Samedi | D54: S01 | E54: Page hors menu | F54: 1 · Piliers B2B | G54: B2B | H54: Page intercommunalité | L54: Collectivités | M54: Nettoyage vitres bâtiments publics Communauté d'Agglomération du Pays Basque | N54: marché nettoyage vitres Pays Basque, laveur de vitres collectivité, nettoyage vitres communes Pays Basque | O54: Nettoyage vitres collectivités Pays Basque | ProVitres-64 | P54: Nettoyage des vitres des bâtiments publics de la Communauté d'Agglomération du Pays Basque : écoles, mairies, salles, équipements. Devis par bâtiment,… | Q54: Nettoyage des vitres des bâtiments publics — Communauté d'Agglomération du Pays Basque | R54: Les communes de l'intercommunalité (Bayonne, Anglet, Biarritz, Hendaye, Saint-Jean-de-Luz, Urrugne…) | Écoles, mairies, gymnases, médiathèques | Vitres en hauteur : perche à eau pure jusqu'à 13 m, nacelle si besoin | Marchés publics et Chorus Pro | Devis | T54: Devis par bâtiment, facturation Chorus Pro, interventions pendant les vacances scolaires | V54: nettoyage-vitres-collectivites-ca-pays-basque | W54: ="https://www.nettoyage-vitres-bayonne.fr/"&V54 | X54: nettoyage-vitres-batiments-publics-pays-basque, contact-devis | Y54: Rédigée | AC54: Page générée le 27/09/2026 — à mettre en ligne
A55: 54 | B55: 46298 | C55: Samedi | D55: S01 | E55: Page hors menu | F55: 1 · Piliers B2B | G55: B2B | H55: Page intercommunalité | L55: Collectivités | M55: Nettoyage vitres bâtiments publics Communauté de communes du Seignanx | N55: marché nettoyage vitres Seignanx, laveur de vitres collectivité, nettoyage vitres communes Seignanx | O55: Nettoyage vitres collectivités Seignanx | ProVitres-64 | P55: Nettoyage des vitres des bâtiments publics de la Communauté de communes du Seignanx : écoles, mairies, salles, équipements. Devis par bâtiment, Chorus… | Q55: Nettoyage des vitres des bâtiments publics — Communauté de communes du Seignanx | R55: Les communes de l'intercommunalité (Tarnos, Ondres, Saint-Martin-de-Seignanx, Saint-André-de-Seignanx, Biaudos, Saint-Laurent-de-Gosse…) | Écoles, mairies, gymnases, médiathèques | Vitres en hauteur : perche à eau pure jusqu'à 13 m, nacelle si besoin | Marchés publics et Chorus Pro | Devis | T55: Devis par bâtiment, facturation Chorus Pro, interventions pendant les vacances scolaires | V55: nettoyage-vitres-collectivites-cc-seignanx | W55: ="https://www.nettoyage-vitres-bayonne.fr/"&V55 | X55: nettoyage-vitres-batiments-publics-pays-basque, contact-devis | Y55: Rédigée | AC55: Page générée le 27/09/2026 — à mettre en ligne
A56: 55 | B56: 46298 | C56: Samedi | D56: S01 | E56: Page hors menu | F56: 1 · Piliers B2B | G56: B2B | H56: Page intercommunalité | L56: Collectivités | M56: Nettoyage vitres bâtiments publics Maremne Adour Côte Sud (MACS) | N56: marché nettoyage vitres MACS, laveur de vitres collectivité, nettoyage vitres communes MACS | O56: Nettoyage vitres collectivités MACS | ProVitres-64 | P56: Nettoyage des vitres des bâtiments publics de la Maremne Adour Côte Sud (MACS) : écoles, mairies, salles, équipements. Devis par bâtiment, Chorus Pro.… | Q56: Nettoyage des vitres des bâtiments publics — Maremne Adour Côte Sud (MACS) | R56: Les communes de l'intercommunalité (Capbreton, Soustons, Saint-Vincent-de-Tyrosse, Labenne, Seignosse, Hossegor…) | Écoles, mairies, gymnases, médiathèques | Vitres en hauteur : perche à eau pure jusqu'à 13 m, nacelle si besoin | Marchés publics et Chorus Pro | Devis | T56: Devis par bâtiment, facturation Chorus Pro, interventions pendant les vacances scolaires | V56: nettoyage-vitres-collectivites-macs | W56: ="https://www.nettoyage-vitres-bayonne.fr/"&V56 | X56: nettoyage-vitres-batiments-publics-pays-basque, contact-devis | Y56: Rédigée | AC56: Page générée le 27/09/2026 — à mettre en ligne
A57: 56 | B57: 46298 | C57: Samedi | D57: S01 | E57: Page hors menu | F57: 1 · Piliers B2B | G57: B2B | H57: Page intercommunalité | L57: Collectivités | M57: Nettoyage vitres bâtiments publics Communauté d'Agglomération du Grand Dax | N57: marché nettoyage vitres Grand Dax, laveur de vitres collectivité, nettoyage vitres communes Grand Dax | O57: Nettoyage vitres collectivités Grand Dax | ProVitres-64 | P57: Nettoyage des vitres des bâtiments publics de la Communauté d'Agglomération du Grand Dax : écoles, mairies, salles, équipements. Devis par bâtiment,… | Q57: Nettoyage des vitres des bâtiments publics — Communauté d'Agglomération du Grand Dax | R57: Les communes de l'intercommunalité (Dax, Saint-Paul-lès-Dax, Saint-Vincent-de-Paul, Narrosse, Mées, Saugnac-et-Cambran…) | Écoles, mairies, gymnases, médiathèques | Vitres en hauteur : perche à eau pure jusqu'à 13 m, nacelle si besoin | Marchés publics et Chorus Pro | Devis | T57: Devis par bâtiment, facturation Chorus Pro, interventions pendant les vacances scolaires | V57: nettoyage-vitres-collectivites-grand-dax | W57: ="https://www.nettoyage-vitres-bayonne.fr/"&V57 | X57: nettoyage-vitres-batiments-publics-pays-basque, contact-devis | Y57: Rédigée | AC57: Page générée le 27/09/2026 — à mettre en ligne
A58: 57 | B58: 46298 | C58: Samedi | D58: S01 | E58: Page hors menu | F58: 1 · Piliers B2B | G58: B2B | H58: Page intercommunalité | L58: Collectivités | M58: Nettoyage vitres bâtiments publics Communauté de communes Pays d'Orthe et Arrigans | N58: marché nettoyage vitres Orthe et Arrigans, laveur de vitres collectivité, nettoyage vitres communes Orthe et Arrigans | O58: Nettoyage vitres collectivités Orthe et Arrigans | P58: Nettoyage des vitres des bâtiments publics de la Communauté de communes Pays d'Orthe et Arrigans : écoles, mairies, salles, équipements. Devis par… | Q58: Nettoyage des vitres des bâtiments publics — Communauté de communes Pays d'Orthe et Arrigans | R58: Les communes de l'intercommunalité (Peyrehorade, Pouillon, Habas, Labatut, Saint-Lon-les-Mines, Port-de-Lanne…) | Écoles, mairies, gymnases, médiathèques | Vitres en hauteur : perche à eau pure jusqu'à 13 m, nacelle si besoin | Marchés publics et Chorus Pro | Devis | T58: Devis par bâtiment, facturation Chorus Pro, interventions pendant les vacances scolaires | V58: nettoyage-vitres-collectivites-pays-orthe-arrigans | W58: ="https://www.nettoyage-vitres-bayonne.fr/"&V58 | X58: nettoyage-vitres-batiments-publics-pays-basque, contact-devis | Y58: Rédigée | AC58: Page générée le 27/09/2026 — à mettre en ligne
A59: 58 | B59: 46298 | C59: Samedi | D59: S01 | E59: Optimisation | F59: 2 · Pages villes (1 par ville) | G59: Mixte | H59: Optimisation page existante | I59: Bayonne | J59: 54306 | K59: BAB urbain (64) | L59: Vitres (tous mots-clés) | M59: Lavage vitres Bayonne | N59: nettoyage vitres Bayonne, laveur de vitres Bayonne, nettoyeur de vitres Bayonne, nettoyage fenêtres Bayonne, vitrerie Bayonne | O59: Lavage & nettoyage vitres Bayonne | ProVitres-64 | P59: Laveur de vitres à Bayonne : lavage et nettoyage de vitres, baies vitrées, vitrines et vitres en hauteur (perche 13 m). Particuliers et pros. Devis gratuit. | Q59: Lavage et nettoyage de vitres à Bayonne | R59: Laveur de vitres à Bayonne : particuliers et professionnels | Lavage des vitres, baies vitrées, vérandas, vitrines | Pollution urbaine et trafic | Vitres en hauteur : perche à eau pure jusqu'à 13 m, nacelle si besoin | Communes voisines : Tarnos, Boucau, Saint-Pierre-d'Irube | Devis gratuit | S59: la poussière urbaine, le trafic et la pollution grisent vite vitrines, façades et baies vitrées | T59: Page déjà en ligne : l'enrichir (600 mots mini), ajouter tous les mots-clés et les liens vers les nouvelles pages de la ville | V59: lavage-vitres-bayonne | W59: ="https://www.nettoyage-vitres-bayonne.fr/"&V59 | X59: entreprise-nettoyage-vitres-bayonne, zone-intervention, contact-devis | Y59: Rédigée | AC59: Page générée le 27/09/2026 — à mettre en ligne
A60: 59 | B60: 46298 | C60: Samedi | D60: S01 | E60: Article | F60: Articles | G60: B2B | H60: Article métier B2B | L60: Mairies & bâtiments communaux | M60: fréquence nettoyage vitres mairie | O60: À quelle fréquence nettoyer les vitres de vos bâtiments | P60: À quelle fréquence nettoyer les vitres de vos bâtiments communaux ? — les conseils de ProVitres-64, laveur de vitres professionnel au Pays Basque et dans… | Q60: À quelle fréquence nettoyer les vitres de vos bâtiments communaux ? | R60: Introduction | Le problème | Les solutions | Notre méthode | Conclusion + demande de devis | V60: blog-actus/a-quelle-frequence-nettoyer-les-vitres-de-vos-batiments-communaux | W60: ="https://www.nettoyage-vitres-bayonne.fr/"&V60 | X60: blog-actus, contact-devis | Y60: Rédigée | AC60: Page générée le 27/09/2026 — à mettre en ligne
A61: 60 | B61: 46298 | C61: Samedi | D61: S01 | E61: Article | F61: Articles | G61: B2B | H61: Article métier B2B | L61: Immeubles & copropriétés | M61: fréquence nettoyage vitres immeuble | O61: À quelle fréquence nettoyer les vitres de votre immeuble ? | P61: À quelle fréquence nettoyer les vitres de votre immeuble ? — les conseils de ProVitres-64, laveur de vitres professionnel au Pays Basque et dans le Sud… | Q61: À quelle fréquence nettoyer les vitres de votre immeuble ? | R61: Introduction | Le problème | Les solutions | Notre méthode | Conclusion + demande de devis | V61: blog-actus/a-quelle-frequence-nettoyer-les-vitres-de-votre-immeuble | W61: ="https://www.nettoyage-vitres-bayonne.fr/"&V61 | X61: blog-actus, contact-devis | Y61: Rédigée | AC61: Page générée le 27/09/2026 — à mettre en ligne
A62: 61 | B62: 46299 | C62: Dimanche | D62: S01 | E62: Optimisation | F62: 2 · Pages villes (1 par ville) | G62: Mixte | H62: Optimisation page existante | I62: Anglet | J62: 43271 | K62: Côte basque (64) | L62: Vitres (tous mots-clés) | M62: Lavage vitres Anglet | N62: nettoyage vitres Anglet, laveur de vitres Anglet, nettoyeur de vitres Anglet, nettoyage fenêtres Anglet, vitrerie Anglet | O62: Lavage & nettoyage vitres Anglet | ProVitres-64 | P62: Laveur de vitres à Anglet : lavage et nettoyage de vitres, baies vitrées, vitrines et vitres en hauteur (perche 13 m). Particuliers et pros. Devis gratuit. | Q62: Lavage et nettoyage de vitres à Anglet | R62: Laveur de vitres à Anglet : particuliers et professionnels | Lavage des vitres, baies vitrées, vérandas, vitrines | Embruns et sel marin | Vitres en hauteur : perche à eau pure jusqu'à 13 m, nacelle si besoin | Communes voisines : Biarritz, Hendaye, Saint-Jean-de-Luz | Devis gratuit | S62: les embruns salés et le sable soulevé par le vent ternissent les vitres face à l'océan en quelques semaines | T62: Page déjà en ligne : l'enrichir (600 mots mini), ajouter tous les mots-clés et les liens vers les nouvelles pages de la ville | V62: lavage-vitres-anglet | W62: ="https://www.nettoyage-vitres-bayonne.fr/"&V62 | X62: entreprise-nettoyage-vitres-anglet, zone-intervention, contact-devis | Y62: Rédigée | AC62: Page générée le 27/09/2026 — à mettre en ligne
A63: 62 | B63: 46299 | C63: Dimanche | D63: S01 | E63: Optimisation | F63: 2 · Pages villes (1 par ville) | G63: Mixte | H63: Optimisation page existante | I63: Biarritz | J63: 26206 | K63: Côte basque (64) | L63: Vitres (tous mots-clés) | M63: Lavage vitres Biarritz | N63: nettoyage vitres Biarritz, laveur de vitres Biarritz, nettoyeur de vitres Biarritz, nettoyage fenêtres Biarritz, vitrerie Biarritz | O63: Lavage & nettoyage vitres Biarritz | ProVitres-64 | P63: Laveur de vitres à Biarritz : lavage et nettoyage de vitres, baies vitrées, vitrines et vitres en hauteur (perche 13 m). Particuliers et pros. Devis gratuit. | Q63: Lavage et nettoyage de vitres à Biarritz | R63: Laveur de vitres à Biarritz : particuliers et professionnels | Lavage des vitres, baies vitrées, vérandas, vitrines | Embruns et sel marin | Vitres en hauteur : perche à eau pure jusqu'à 13 m, nacelle si besoin | Communes voisines : Anglet, Hendaye, Saint-Jean-de-Luz | Devis gratuit | S63: les embruns salés et le sable soulevé par le vent ternissent les vitres face à l'océan en quelques semaines | T63: Page déjà en ligne : l'enrichir (600 mots mini), ajouter tous les mots-clés et les liens vers les nouvelles pages de la ville | V63: lavage-vitres-biarritz | W63: ="https://www.nettoyage-vitres-bayonne.fr/"&V63 | X63: entreprise-nettoyage-vitres-biarritz, zone-intervention, contact-devis | Y63: Rédigée | AC63: Page générée le 27/09/2026 — à mettre en ligne
A64: 63 | B64: 46299 | C64: Dimanche | D64: S01 | E64: Optimisation | F64: 2 · Pages villes (1 par ville) | G64: Mixte | H64: Optimisation page existante | I64: Dax | J64: 22109 | K64: Dax thermal (40) | L64: Vitres (tous mots-clés) | M64: Lavage vitres Dax | N64: nettoyage vitres Dax, laveur de vitres Dax, nettoyeur de vitres Dax, nettoyage fenêtres Dax, vitrerie Dax | O64: Lavage & nettoyage vitres Dax | ProVitres-64 | P64: Laveur de vitres à Dax : lavage et nettoyage de vitres, baies vitrées, vitrines et vitres en hauteur (perche 13 m). Particuliers et pros. Devis gratuit. | Q64: Lavage et nettoyage de vitres à Dax | R64: Laveur de vitres à Dax : particuliers et professionnels | Lavage des vitres, baies vitrées, vérandas, vitrines | Ville thermale et calcaire | Vitres en hauteur : perche à eau pure jusqu'à 13 m, nacelle si besoin | Communes voisines : Saint-Paul-lès-Dax | Devis gratuit | S64: hôtels, résidences de curistes et établissements de soins demandent des vitres irréprochables malgré une eau très calcaire | T64: Page déjà en ligne : l'enrichir (600 mots mini), ajouter tous les mots-clés et les liens vers les nouvelles pages de la ville | V64: lavage-vitres-dax | W64: ="https://www.nettoyage-vitres-bayonne.fr/"&V64 | X64: entreprise-nettoyage-vitres-dax, zone-intervention, contact-devis | Y64: Rédigée | AC64: Page générée le 27/09/2026 — à mettre en ligne
A65: 64 | B65: 46299 | C65: Dimanche | D65: S01 | E65: Optimisation | F65: 2 · Pages villes (1 par ville) | G65: Mixte | H65: Optimisation page existante | I65: Hendaye | J65: 18102 | K65: Côte basque (64) | L65: Vitres (tous mots-clés) | M65: Lavage vitres Hendaye | N65: nettoyage vitres Hendaye, laveur de vitres Hendaye, nettoyeur de vitres Hendaye, nettoyage fenêtres Hendaye, vitrerie Hendaye | O65: Lavage & nettoyage vitres Hendaye | ProVitres-64 | P65: Laveur de vitres à Hendaye : lavage et nettoyage de vitres, baies vitrées, vitrines et vitres en hauteur (perche 13 m). Particuliers et pros. Devis gratuit. | Q65: Lavage et nettoyage de vitres à Hendaye | R65: Laveur de vitres à Hendaye : particuliers et professionnels | Lavage des vitres, baies vitrées, vérandas, vitrines | Embruns et sel marin | Vitres en hauteur : perche à eau pure jusqu'à 13 m, nacelle si besoin | Communes voisines : Anglet, Biarritz, Saint-Jean-de-Luz | Devis gratuit | S65: les embruns salés et le sable soulevé par le vent ternissent les vitres face à l'océan en quelques semaines | T65: Page déjà en ligne : l'enrichir (600 mots mini), ajouter tous les mots-clés et les liens vers les nouvelles pages de la ville | V65: lavage-vitres-hendaye | W65: ="https://www.nettoyage-vitres-bayonne.fr/"&V65 | X65: entreprise-nettoyage-vitres-hendaye, zone-intervention, contact-devis | Y65: Rédigée | AC65: Page générée le 27/09/2026 — à mettre en ligne
A66: 65 | B66: 46299 | C66: Dimanche | D66: S01 | E66: Optimisation | F66: 2 · Pages villes (1 par ville) | G66: Mixte | H66: Optimisation page existante | I66: Saint-Jean-de-Luz | J66: 14857 | K66: Côte basque (64) | L66: Vitres (tous mots-clés) | M66: Lavage vitres Saint-Jean-de-Luz | N66: nettoyage vitres Saint-Jean-de-Luz, laveur de vitres Saint-Jean-de-Luz, nettoyeur de vitres Saint-Jean-de-Luz, nettoyage fenêtres Saint-Jean-de-Luz, vitrerie Saint-Jean-de-Luz | O66: Lavage & nettoyage vitres Saint-Jean-de-Luz | ProVitres-64 | P66: Laveur de vitres à Saint-Jean-de-Luz : lavage et nettoyage de vitres, baies vitrées, vitrines et vitres en hauteur (perche 13 m). Particuliers et pros.… | Q66: Lavage et nettoyage de vitres à Saint-Jean-de-Luz | R66: Laveur de vitres à Saint-Jean-de-Luz : particuliers et professionnels | Lavage des vitres, baies vitrées, vérandas, vitrines | Embruns et sel marin | Vitres en hauteur : perche à eau pure jusqu'à 13 m, nacelle si besoin | Communes voisines : Ciboure, Anglet, Biarritz | Devis gratuit | S66: les embruns salés et le sable soulevé par le vent ternissent les vitres face à l'océan en quelques semaines | T66: Page déjà en ligne : l'enrichir (600 mots mini), ajouter tous les mots-clés et les liens vers les nouvelles pages de la ville | V66: lavage-vitres-saint-jean-de-luz | W66: ="https://www.nettoyage-vitres-bayonne.fr/"&V66 | X66: entreprise-nettoyage-vitres-saint-jean-de-luz, zone-intervention, contact-devis | Y66: Rédigée | AC66: Page générée le 27/09/2026 — à mettre en ligne
A67: 66 | B67: 46299 | C67: Dimanche | D67: S01 | E67: Page hors menu | F67: 2 · Pages villes (1 par ville) | G67: Mixte | H67: Page ville principale | I67: Saint-Paul-lès-Dax | J67: 14481 | K67: Dax thermal (40) | L67: Vitres (tous mots-clés) | M67: Nettoyage vitres Saint-Paul-lès-Dax | N67: lavage vitres Saint-Paul-lès-Dax, laveur de vitres Saint-Paul-lès-Dax, nettoyeur de vitres Saint-Paul-lès-Dax, nettoyage fenêtres Saint-Paul-lès-Dax, vitrerie Saint-Paul-lès-Dax | O67: Nettoyage & lavage vitres Saint-Paul-lès-Dax | ProVitres-64 | P67: Laveur de vitres à Saint-Paul-lès-Dax (40990) : nettoyage et lavage de vitres, baies vitrées, vitrines et vitres en hauteur. Particuliers et pros. Devis… | Q67: Nettoyage et lavage de vitres à Saint-Paul-lès-Dax | R67: Laveur de vitres à Saint-Paul-lès-Dax : particuliers et professionnels | Lavage des vitres, baies vitrées, vérandas, vitrines | Ville thermale et calcaire | Vitres en hauteur : perche à eau pure jusqu'à 13 m, nacelle si besoin | Communes voisines : Dax | Devis gratuit | S67: hôtels, résidences de curistes et établissements de soins demandent des vitres irréprochables malgré une eau très calcaire | T67: Vitres en hauteur : perche à eau pure jusqu'à 13 m, nacelle si besoin | V67: nettoyage-vitres-saint-paul-les-dax | W67: ="https://www.nettoyage-vitres-bayonne.fr/"&V67 | X67: zone-intervention, contact-devis | Y67: Rédigée | AC67: Page générée le 27/09/2026 — à mettre en ligne
A68: 67 | B68: 46299 | C68: Dimanche | D68: S01 | E68: Page hors menu | F68: 2 · Pages villes (1 par ville) | G68: Mixte | H68: Page ville principale | I68: Tarnos | J68: 12957 | K68: BAB urbain (40) | L68: Vitres (tous mots-clés) | M68: Nettoyage vitres Tarnos | N68: lavage vitres Tarnos, laveur de vitres Tarnos, nettoyeur de vitres Tarnos, nettoyage fenêtres Tarnos, vitrerie Tarnos | O68: Nettoyage & lavage vitres Tarnos | ProVitres-64 | P68: Laveur de vitres à Tarnos (40220) : nettoyage et lavage de vitres, baies vitrées, vitrines et vitres en hauteur. Particuliers et pros. Devis gratuit. | Q68: Nettoyage et lavage de vitres à Tarnos | R68: Laveur de vitres à Tarnos : particuliers et professionnels | Lavage des vitres, baies vitrées, vérandas, vitrines | Pollution urbaine et trafic | Vitres en hauteur : perche à eau pure jusqu'à 13 m, nacelle si besoin | Communes voisines : Bayonne, Boucau, Saint-Pierre-d'Irube | Devis gratuit | S68: la poussière urbaine, le trafic et la pollution grisent vite vitrines, façades et baies vitrées | T68: Vitres en hauteur : perche à eau pure jusqu'à 13 m, nacelle si besoin | V68: nettoyage-vitres-tarnos | W68: ="https://www.nettoyage-vitres-bayonne.fr/"&V68 | X68: zone-intervention, contact-devis | Y68: Rédigée | AC68: Page générée le 27/09/2026 — à mettre en ligne
A69: 68 | B69: 46299 | C69: Dimanche | D69: S01 | E69: Optimisation | F69: 2 · Pages villes (1 par ville) | G69: Mixte | H69: Optimisation page existante | I69: Urrugne | J69: 10661 | K69: Côte basque (64) | L69: Vitres (tous mots-clés) | M69: Lavage vitres Urrugne | N69: nettoyage vitres Urrugne, laveur de vitres Urrugne, nettoyeur de vitres Urrugne, nettoyage fenêtres Urrugne, vitrerie Urrugne | O69: Lavage & nettoyage vitres Urrugne | ProVitres-64 | P69: Laveur de vitres à Urrugne : lavage et nettoyage de vitres, baies vitrées, vitrines et vitres en hauteur (perche 13 m). Particuliers et pros. Devis gratuit. | Q69: Lavage et nettoyage de vitres à Urrugne | R69: Laveur de vitres à Urrugne : particuliers et professionnels | Lavage des vitres, baies vitrées, vérandas, vitrines | Embruns et sel marin | Vitres en hauteur : perche à eau pure jusqu'à 13 m, nacelle si besoin | Communes voisines : Anglet, Biarritz, Hendaye | Devis gratuit | S69: les embruns salés et le sable soulevé par le vent ternissent les vitres face à l'océan en quelques semaines | T69: Page déjà en ligne : l'enrichir (600 mots mini), ajouter tous les mots-clés et les liens vers les nouvelles pages de la ville | V69: lavage-vitres-urrugne | W69: ="https://www.nettoyage-vitres-bayonne.fr/"&V69 | X69: entreprise-nettoyage-vitres-urrugne, zone-intervention, contact-devis | Y69: Rédigée | AC69: Page générée le 27/09/2026 — à mettre en ligne
A70: 69 | B70: 46299 | C70: Dimanche | D70: S01 | E70: Article | F70: Articles | G70: B2B | H70: Article métier B2B | L70: Commerces & boutiques | M70: fréquence nettoyage vitres magasin | O70: À quelle fréquence nettoyer les vitres de votre commerce ? | P70: À quelle fréquence nettoyer les vitres de votre commerce ? — les conseils de ProVitres-64, laveur de vitres professionnel au Pays Basque et dans le Sud… | Q70: À quelle fréquence nettoyer les vitres de votre commerce ? | R70: Introduction | Le problème | Les solutions | Notre méthode | Conclusion + demande de devis | V70: blog-actus/a-quelle-frequence-nettoyer-les-vitres-de-votre-commerce | W70: ="https://www.nettoyage-vitres-bayonne.fr/"&V70 | X70: blog-actus, contact-devis | Y70: Rédigée | AC70: Page générée le 27/09/2026 — à mettre en ligne
A71: 70 | B71: 46299 | C71: Dimanche | D71: S01 | E71: Article | F71: Articles | G71: B2B | H71: Article métier B2B | L71: Hôtels & résidences | M71: fréquence nettoyage vitres hôtel | O71: À quelle fréquence nettoyer les vitres de votre hôtel ? | P71: À quelle fréquence nettoyer les vitres de votre hôtel ? — les conseils de ProVitres-64, laveur de vitres professionnel au Pays Basque et dans le Sud Landes. | Q71: À quelle fréquence nettoyer les vitres de votre hôtel ? | R71: Introduction | Le problème | Les solutions | Notre méthode | Conclusion + demande de devis | V71: blog-actus/a-quelle-frequence-nettoyer-les-vitres-de-votre-hotel | W71: ="https://www.nettoyage-vitres-bayonne.fr/"&V71 | X71: blog-actus, contact-devis | Y71: Rédigée | AC71: Page générée le 27/09/2026 — à mettre en ligne
A72: 71 | B72: 46300 | C72: Lundi | D72: S02 | E72: Page hors menu | F72: 2 · Pages villes (1 par ville) | G72: Mixte | H72: Page ville principale | I72: Capbreton | J72: 9184 | K72: Côte landaise (40) | L72: Vitres (tous mots-clés) | M72: Nettoyage vitres Capbreton | N72: lavage vitres Capbreton, laveur de vitres Capbreton, nettoyeur de vitres Capbreton, nettoyage fenêtres Capbreton, vitrerie Capbreton | O72: Nettoyage & lavage vitres Capbreton | ProVitres-64 | P72: Laveur de vitres à Capbreton (40130) : nettoyage et lavage de vitres, baies vitrées, vitrines et vitres en hauteur. Particuliers et pros. Devis gratuit. | Q72: Nettoyage et lavage de vitres à Capbreton | R72: Laveur de vitres à Capbreton : particuliers et professionnels | Lavage des vitres, baies vitrées, vérandas, vitrines | Sable, sel et pollen de pin | Vitres en hauteur : perche à eau pure jusqu'à 13 m, nacelle si besoin | Communes voisines : Soustons, Labenne, Ondres | Devis gratuit | S72: le sable, le sel et le pollen de pin forment un film collant sur les baies vitrées des villas et résidences | T72: Vitres en hauteur : perche à eau pure jusqu'à 13 m, nacelle si besoin | V72: nettoyage-vitres-capbreton | W72: ="https://www.nettoyage-vitres-bayonne.fr/"&V72 | X72: zone-intervention, contact-devis | Y72: À créer
A73: 72 | B73: 46300 | C73: Lundi | D73: S02 | E73: Optimisation | F73: 2 · Pages villes (1 par ville) | G73: Mixte | H73: Optimisation page existante | I73: Boucau | J73: 8968 | K73: BAB urbain (64) | L73: Vitres (tous mots-clés) | M73: Lavage vitres Boucau | N73: nettoyage vitres Boucau, laveur de vitres Boucau, nettoyeur de vitres Boucau, nettoyage fenêtres Boucau, vitrerie Boucau | O73: Lavage & nettoyage vitres Boucau | ProVitres-64 | P73: Laveur de vitres à Boucau : lavage et nettoyage de vitres, baies vitrées, vitrines et vitres en hauteur (perche 13 m). Particuliers et pros. Devis gratuit. | Q73: Lavage et nettoyage de vitres à Boucau | R73: Laveur de vitres à Boucau : particuliers et professionnels | Lavage des vitres, baies vitrées, vérandas, vitrines | Pollution urbaine et trafic | Vitres en hauteur : perche à eau pure jusqu'à 13 m, nacelle si besoin | Communes voisines : Bayonne, Tarnos, Saint-Pierre-d'Irube | Devis gratuit | S73: la poussière urbaine, le trafic et la pollution grisent vite vitrines, façades et baies vitrées | T73: Page déjà en ligne : l'enrichir (600 mots mini), ajouter tous les mots-clés et les liens vers les nouvelles pages de la ville | V73: lavage-vitres-boucau | W73: ="https://www.nettoyage-vitres-bayonne.fr/"&V73 | X73: entreprise-nettoyage-vitres-boucau, zone-intervention, contact-devis | Y73: À créer
A74: 73 | B74: 46300 | C74: Lundi | D74: S02 | E74: Page hors menu | F74: 2 · Pages villes (1 par ville) | G74: Mixte | H74: Page ville principale | I74: Soustons | J74: 8701 | K74: Côte landaise (40) | L74: Vitres (tous mots-clés) | M74: Nettoyage vitres Soustons | N74: lavage vitres Soustons, laveur de vitres Soustons, nettoyeur de vitres Soustons, nettoyage fenêtres Soustons, vitrerie Soustons | O74: Nettoyage & lavage vitres Soustons | ProVitres-64 | P74: Laveur de vitres à Soustons (40140) : nettoyage et lavage de vitres, baies vitrées, vitrines et vitres en hauteur. Particuliers et pros. Devis gratuit. | Q74: Nettoyage et lavage de vitres à Soustons | R74: Laveur de vitres à Soustons : particuliers et professionnels | Lavage des vitres, baies vitrées, vérandas, vitrines | Sable, sel et pollen de pin | Vitres en hauteur : perche à eau pure jusqu'à 13 m, nacelle si besoin | Communes voisines : Azur, Capbreton, Labenne, Azur | Devis gratuit | S74: le sable, le sel et le pollen de pin forment un film collant sur les baies vitrées des villas et résidences | T74: Vitres en hauteur : perche à eau pure jusqu'à 13 m, nacelle si besoin | U74: Azur | V74: nettoyage-vitres-soustons | W74: ="https://www.nettoyage-vitres-bayonne.fr/"&V74 | X74: zone-intervention, contact-devis | Y74: À créer
A75: 74 | B75: 46300 | C75: Lundi | D75: S02 | E75: Page hors menu | F75: 2 · Pages villes (1 par ville) | G75: Mixte | H75: Page ville principale | I75: Saint-Vincent-de-Tyrosse | J75: 8014 | K75: Landes intérieures (40) | L75: Vitres (tous mots-clés) | M75: Nettoyage vitres Saint-Vincent-de-Tyrosse | N75: lavage vitres Saint-Vincent-de-Tyrosse, laveur de vitres Saint-Vincent-de-Tyrosse, nettoyeur de vitres Saint-Vincent-de-Tyrosse, nettoyage fenêtres Saint-Vincent-de-Tyrosse, vitrerie Saint-Vincent-de-Tyrosse | O75: Nettoyage & lavage vitres Saint-Vincent-de-Tyrosse | P75: Laveur de vitres à Saint-Vincent-de-Tyrosse (40230) : nettoyage et lavage de vitres, baies vitrées, vitrines et vitres en hauteur. Particuliers et pros.… | Q75: Nettoyage et lavage de vitres à Saint-Vincent-de-Tyrosse | R75: Laveur de vitres à Saint-Vincent-de-Tyrosse : particuliers et professionnels | Lavage des vitres, baies vitrées, vérandas, vitrines | Pollen de pin et résine | Vitres en hauteur : perche à eau pure jusqu'à 13 m, nacelle si besoin | Communes voisines : Bénesse-Maremne, Tosse, Saint-Geours-de-Maremne, Orx | Devis gratuit | S75: le pollen de pin au printemps (dépôt jaune) et la résine de la forêt landaise encrassent les vitrages | T75: Vitres en hauteur : perche à eau pure jusqu'à 13 m, nacelle si besoin | U75: Orx | V75: nettoyage-vitres-saint-vincent-de-tyrosse | W75: ="https://www.nettoyage-vitres-bayonne.fr/"&V75 | X75: zone-intervention, contact-devis | Y75: À créer
A76: 75 | B76: 46300 | C76: Lundi | D76: S02 | E76: Optimisation | F76: 2 · Pages villes (1 par ville) | G76: Mixte | H76: Optimisation page existante | I76: Ustaritz | J76: 7897 | K76: Labourd intérieur (64) | L76: Vitres (tous mots-clés) | M76: Lavage vitres Ustaritz | N76: nettoyage vitres Ustaritz, laveur de vitres Ustaritz, nettoyeur de vitres Ustaritz, nettoyage fenêtres Ustaritz, vitrerie Ustaritz | O76: Lavage & nettoyage vitres Ustaritz | ProVitres-64 | P76: Laveur de vitres à Ustaritz : lavage et nettoyage de vitres, baies vitrées, vitrines et vitres en hauteur (perche 13 m). Particuliers et pros. Devis gratuit. | Q76: Lavage et nettoyage de vitres à Ustaritz | R76: Laveur de vitres à Ustaritz : particuliers et professionnels | Lavage des vitres, baies vitrées, vérandas, vitrines | Pollen, poussière agricole et calcaire | Vitres en hauteur : perche à eau pure jusqu'à 13 m, nacelle si besoin | Communes voisines : Larressore, Jatxou, Halsou, Halsou | Devis gratuit | S76: maisons labourdines aux menuiseries colorées, pollen, poussière des champs et eau calcaire laissent des traces | T76: Page déjà en ligne : l'enrichir (600 mots mini), ajouter tous les mots-clés et les liens vers les nouvelles pages de la ville | U76: Halsou | V76: lavage-vitres-ustaritz | W76: ="https://www.nettoyage-vitres-bayonne.fr/"&V76 | X76: entreprise-nettoyage-vitres-ustaritz, zone-intervention, contact-devis | Y76: À créer
A77: 76 | B77: 46300 | C77: Lundi | D77: S02 | E77: Optimisation | F77: 2 · Pages villes (1 par ville) | G77: Mixte | H77: Optimisation page existante | I77: Bidart | J77: 7689 | K77: Côte basque (64) | L77: Vitres (tous mots-clés) | M77: Lavage vitres Bidart | N77: nettoyage vitres Bidart, laveur de vitres Bidart, nettoyeur de vitres Bidart, nettoyage fenêtres Bidart, vitrerie Bidart | O77: Lavage & nettoyage vitres Bidart | ProVitres-64 | P77: Laveur de vitres à Bidart : lavage et nettoyage de vitres, baies vitrées, vitrines et vitres en hauteur (perche 13 m). Particuliers et pros. Devis gratuit. | Q77: Lavage et nettoyage de vitres à Bidart | R77: Laveur de vitres à Bidart : particuliers et professionnels | Lavage des vitres, baies vitrées, vérandas, vitrines | Embruns et sel marin | Vitres en hauteur : perche à eau pure jusqu'à 13 m, nacelle si besoin | Communes voisines : Guéthary, Anglet, Biarritz | Devis gratuit | S77: les embruns salés et le sable soulevé par le vent ternissent les vitres face à l'océan en quelques semaines | T77: Page déjà en ligne : l'enrichir (600 mots mini), ajouter tous les mots-clés et les liens vers les nouvelles pages de la ville | V77: lavage-vitres-bidart | W77: ="https://www.nettoyage-vitres-bayonne.fr/"&V77 | X77: entreprise-nettoyage-vitres-bidart, zone-intervention, contact-devis | Y77: À créer
A78: 77 | B78: 46300 | C78: Lundi | D78: S02 | E78: Optimisation | F78: 2 · Pages villes (1 par ville) | G78: Mixte | H78: Optimisation page existante | I78: Hasparren | J78: 7626 | K78: Labourd intérieur (64) | L78: Vitres (tous mots-clés) | M78: Lavage vitres Hasparren | N78: nettoyage vitres Hasparren, laveur de vitres Hasparren, nettoyeur de vitres Hasparren, nettoyage fenêtres Hasparren, vitrerie Hasparren | O78: Lavage & nettoyage vitres Hasparren | ProVitres-64 | P78: Laveur de vitres à Hasparren : lavage et nettoyage de vitres, baies vitrées, vitrines et vitres en hauteur (perche 13 m). Particuliers et pros. Devis gratuit. | Q78: Lavage et nettoyage de vitres à Hasparren | R78: Laveur de vitres à Hasparren : particuliers et professionnels | Lavage des vitres, baies vitrées, vérandas, vitrines | Pollen, poussière agricole et calcaire | Vitres en hauteur : perche à eau pure jusqu'à 13 m, nacelle si besoin | Communes voisines : Briscous, Urt, Ayherre | Devis gratuit | S78: maisons labourdines aux menuiseries colorées, pollen, poussière des champs et eau calcaire laissent des traces | T78: Page déjà en ligne : l'enrichir (600 mots mini), ajouter tous les mots-clés et les liens vers les nouvelles pages de la ville | V78: lavage-vitres-hasparren | W78: ="https://www.nettoyage-vitres-bayonne.fr/"&V78 | X78: entreprise-nettoyage-vitres-hasparren, zone-intervention, contact-devis | Y78: À créer
A79: 78 | B79: 46300 | C79: Lundi | D79: S02 | E79: Optimisation | F79: 2 · Pages villes (1 par ville) | G79: Mixte | H79: Optimisation page existante | I79: Saint-Pée-sur-Nivelle | J79: 7264 | K79: Labourd intérieur (64) | L79: Vitres (tous mots-clés) | M79: Lavage vitres Saint-Pée-sur-Nivelle | N79: nettoyage vitres Saint-Pée-sur-Nivelle, laveur de vitres Saint-Pée-sur-Nivelle, nettoyeur de vitres Saint-Pée-sur-Nivelle, nettoyage fenêtres Saint-Pée-sur-Nivelle, vitrerie Saint-Pée-sur-Nivelle | O79: Lavage & nettoyage vitres Saint-Pée-sur-Nivelle | P79: Laveur de vitres à Saint-Pée-sur-Nivelle : lavage et nettoyage de vitres, baies vitrées, vitrines et vitres en hauteur (perche 13 m). Particuliers et… | Q79: Lavage et nettoyage de vitres à Saint-Pée-sur-Nivelle | R79: Laveur de vitres à Saint-Pée-sur-Nivelle : particuliers et professionnels | Lavage des vitres, baies vitrées, vérandas, vitrines | Pollen, poussière agricole et calcaire | Vitres en hauteur : perche à eau pure jusqu'à 13 m, nacelle si besoin | Communes voisines : Ascain, Sare, Ustaritz | Devis gratuit | S79: maisons labourdines aux menuiseries colorées, pollen, poussière des champs et eau calcaire laissent des traces | T79: Page déjà en ligne : l'enrichir (600 mots mini), ajouter tous les mots-clés et les liens vers les nouvelles pages de la ville | V79: lavage-vitres-saint-pee-sur-nivelle | W79: ="https://www.nettoyage-vitres-bayonne.fr/"&V79 | X79: entreprise-nettoyage-vitres-saint-pee-sur-nivelle, zone-intervention, contact-devis | Y79: À créer
A80: 79 | B80: 46300 | C80: Lundi | D80: S02 | E80: Article | F80: Articles | G80: B2B | H80: Article métier B2B | L80: Bureaux & entreprises | M80: fréquence nettoyage vitres bureaux | O80: À quelle fréquence nettoyer les vitres de vos bureaux ? | P80: À quelle fréquence nettoyer les vitres de vos bureaux ? — les conseils de ProVitres-64, laveur de vitres professionnel au Pays Basque et dans le Sud Landes. | Q80: À quelle fréquence nettoyer les vitres de vos bureaux ? | R80: Introduction | Le problème | Les solutions | Notre méthode | Conclusion + demande de devis | V80: blog-actus/a-quelle-frequence-nettoyer-les-vitres-de-vos-bureaux | W80: ="https://www.nettoyage-vitres-bayonne.fr/"&V80 | X80: blog-actus, contact-devis | Y80: À créer
A81: 80 | B81: 46300 | C81: Lundi | D81: S02 | E81: Article | F81: Articles | G81: B2B | H81: Article métier B2B | L81: Restaurants, bars & cafés | M81: fréquence nettoyage vitres restaurant | O81: À quelle fréquence nettoyer les vitres de votre restaurant ? | P81: À quelle fréquence nettoyer les vitres de votre restaurant ? — les conseils de ProVitres-64, laveur de vitres professionnel au Pays Basque et dans le Sud… | Q81: À quelle fréquence nettoyer les vitres de votre restaurant ? | R81: Introduction | Le problème | Les solutions | Notre méthode | Conclusion + demande de devis | V81: blog-actus/a-quelle-frequence-nettoyer-les-vitres-de-votre-restaurant | W81: ="https://www.nettoyage-vitres-bayonne.fr/"&V81 | X81: blog-actus, contact-devis | Y81: À créer
A82: 81 | B82: 46301 | C82: Mardi | D82: S02 | E82: Page hors menu | F82: 2 · Pages villes (1 par ville) | G82: Mixte | H82: Page ville principale | I82: Labenne | J82: 7183 | K82: Côte landaise (40) | L82: Vitres (tous mots-clés) | M82: Nettoyage vitres Labenne | N82: lavage vitres Labenne, laveur de vitres Labenne, nettoyeur de vitres Labenne, nettoyage fenêtres Labenne, vitrerie Labenne | O82: Nettoyage & lavage vitres Labenne | ProVitres-64 | P82: Laveur de vitres à Labenne (40530) : nettoyage et lavage de vitres, baies vitrées, vitrines et vitres en hauteur. Particuliers et pros. Devis gratuit. | Q82: Nettoyage et lavage de vitres à Labenne | R82: Laveur de vitres à Labenne : particuliers et professionnels | Lavage des vitres, baies vitrées, vérandas, vitrines | Sable, sel et pollen de pin | Vitres en hauteur : perche à eau pure jusqu'à 13 m, nacelle si besoin | Communes voisines : Capbreton, Soustons, Ondres | Devis gratuit | S82: le sable, le sel et le pollen de pin forment un film collant sur les baies vitrées des villas et résidences | T82: Vitres en hauteur : perche à eau pure jusqu'à 13 m, nacelle si besoin | V82: nettoyage-vitres-labenne | W82: ="https://www.nettoyage-vitres-bayonne.fr/"&V82 | X82: zone-intervention, contact-devis | Y82: À créer
A83: 82 | B83: 46301 | C83: Mardi | D83: S02 | E83: Optimisation | F83: 2 · Pages villes (1 par ville) | G83: Mixte | H83: Optimisation page existante | I83: Cambo-les-Bains | J83: 6760 | K83: Labourd intérieur (64) | L83: Vitres (tous mots-clés) | M83: Lavage vitres Cambo-les-Bains | N83: nettoyage vitres Cambo-les-Bains, laveur de vitres Cambo-les-Bains, nettoyeur de vitres Cambo-les-Bains, nettoyage fenêtres Cambo-les-Bains, vitrerie Cambo-les-Bains | O83: Lavage & nettoyage vitres Cambo-les-Bains | ProVitres-64 | P83: Laveur de vitres à Cambo-les-Bains : lavage et nettoyage de vitres, baies vitrées, vitrines et vitres en hauteur (perche 13 m). Particuliers et pros.… | Q83: Lavage et nettoyage de vitres à Cambo-les-Bains | R83: Laveur de vitres à Cambo-les-Bains : particuliers et professionnels | Lavage des vitres, baies vitrées, vérandas, vitrines | Pollen, poussière agricole et calcaire | Vitres en hauteur : perche à eau pure jusqu'à 13 m, nacelle si besoin | Communes voisines : Itxassou, Espelette, Souraïde, Louhossoa, Ainhoa | Devis gratuit | S83: maisons labourdines aux menuiseries colorées, pollen, poussière des champs et eau calcaire laissent des traces | T83: Page déjà en ligne : l'enrichir (600 mots mini), ajouter tous les mots-clés et les liens vers les nouvelles pages de la ville | U83: Louhossoa, Ainhoa | V83: lavage-vitres-cambo-les-bains | W83: ="https://www.nettoyage-vitres-bayonne.fr/"&V83 | X83: entreprise-nettoyage-vitres-cambo-les-bains, zone-intervention, contact-devis | Y83: À créer
A84: 83 | B84: 46301 | C84: Mardi | D84: S02 | E84: Page hors menu | F84: 2 · Pages villes (1 par ville) | G84: Mixte | H84: Page ville principale | I84: Ondres | J84: 6533 | K84: Côte landaise (40) | L84: Vitres (tous mots-clés) | M84: Nettoyage vitres Ondres | N84: lavage vitres Ondres, laveur de vitres Ondres, nettoyeur de vitres Ondres, nettoyage fenêtres Ondres, vitrerie Ondres | O84: Nettoyage & lavage vitres Ondres | ProVitres-64 | P84: Laveur de vitres à Ondres (40440) : nettoyage et lavage de vitres, baies vitrées, vitrines et vitres en hauteur. Particuliers et pros. Devis gratuit. | Q84: Nettoyage et lavage de vitres à Ondres | R84: Laveur de vitres à Ondres : particuliers et professionnels | Lavage des vitres, baies vitrées, vérandas, vitrines | Sable, sel et pollen de pin | Vitres en hauteur : perche à eau pure jusqu'à 13 m, nacelle si besoin | Communes voisines : Capbreton, Soustons, Labenne | Devis gratuit | S84: le sable, le sel et le pollen de pin forment un film collant sur les baies vitrées des villas et résidences | T84: Vitres en hauteur : perche à eau pure jusqu'à 13 m, nacelle si besoin | V84: nettoyage-vitres-ondres | W84: ="https://www.nettoyage-vitres-bayonne.fr/"&V84 | X84: zone-intervention, contact-devis | Y84: À créer
A85: 84 | B85: 46301 | C85: Mardi | D85: S02 | E85: Page hors menu | F85: 2 · Pages villes (1 par ville) | G85: Mixte | H85: Page ville principale | I85: Saint-Martin-de-Seignanx | J85: 6238 | K85: Landes intérieures (40) | L85: Vitres (tous mots-clés) | M85: Nettoyage vitres Saint-Martin-de-Seignanx | N85: lavage vitres Saint-Martin-de-Seignanx, laveur de vitres Saint-Martin-de-Seignanx, nettoyeur de vitres Saint-Martin-de-Seignanx, nettoyage fenêtres Saint-Martin-de-Seignanx, vitrerie Saint-Martin-de-Seignanx | O85: Nettoyage & lavage vitres Saint-Martin-de-Seignanx | P85: Laveur de vitres à Saint-Martin-de-Seignanx (40390) : nettoyage et lavage de vitres, baies vitrées, vitrines et vitres en hauteur. Particuliers et pros.… | Q85: Nettoyage et lavage de vitres à Saint-Martin-de-Seignanx | R85: Laveur de vitres à Saint-Martin-de-Seignanx : particuliers et professionnels | Lavage des vitres, baies vitrées, vérandas, vitrines | Pollen de pin et résine | Vitres en hauteur : perche à eau pure jusqu'à 13 m, nacelle si besoin | Communes voisines : Saint-André-de-Seignanx, Saint-Martin-de-Hinx, Sainte-Marie-de-Gosse | Devis gratuit | S85: le pollen de pin au printemps (dépôt jaune) et la résine de la forêt landaise encrassent les vitrages | T85: Vitres en hauteur : perche à eau pure jusqu'à 13 m, nacelle si besoin | V85: nettoyage-vitres-saint-martin-de-seignanx | W85: ="https://www.nettoyage-vitres-bayonne.fr/"&V85 | X85: zone-intervention, contact-devis | Y85: À créer
A86: 85 | B86: 46301 | C86: Mardi | D86: S02 | E86: Optimisation | F86: 2 · Pages villes (1 par ville) | G86: Mixte | H86: Optimisation page existante | I86: Ciboure | J86: 5951 | K86: Côte basque (64) | L86: Vitres (tous mots-clés) | M86: Lavage vitres Ciboure | N86: nettoyage vitres Ciboure, laveur de vitres Ciboure, nettoyeur de vitres Ciboure, nettoyage fenêtres Ciboure, vitrerie Ciboure | O86: Lavage & nettoyage vitres Ciboure | ProVitres-64 | P86: Laveur de vitres à Ciboure : lavage et nettoyage de vitres, baies vitrées, vitrines et vitres en hauteur (perche 13 m). Particuliers et pros. Devis gratuit. | Q86: Lavage et nettoyage de vitres à Ciboure | R86: Laveur de vitres à Ciboure : particuliers et professionnels | Lavage des vitres, baies vitrées, vérandas, vitrines | Embruns et sel marin | Vitres en hauteur : perche à eau pure jusqu'à 13 m, nacelle si besoin | Communes voisines : Saint-Jean-de-Luz, Anglet, Biarritz | Devis gratuit | S86: les embruns salés et le sable soulevé par le vent ternissent les vitres face à l'océan en quelques semaines | T86: Page déjà en ligne : l'enrichir (600 mots mini), ajouter tous les mots-clés et les liens vers les nouvelles pages de la ville | V86: lavage-vitres-ciboure | W86: ="https://www.nettoyage-vitres-bayonne.fr/"&V86 | X86: entreprise-nettoyage-vitres-ciboure, zone-intervention, contact-devis | Y86: À créer
A87: 86 | B87: 46301 | C87: Mardi | D87: S02 | E87: Optimisation | F87: 2 · Pages villes (1 par ville) | G87: Mixte | H87: Optimisation page existante | I87: Saint-Pierre-d'Irube | J87: 5900 | K87: BAB urbain (64) | L87: Vitres (tous mots-clés) | M87: Lavage vitres Saint-Pierre-d'Irube | N87: nettoyage vitres Saint-Pierre-d'Irube, laveur de vitres Saint-Pierre-d'Irube, nettoyeur de vitres Saint-Pierre-d'Irube, nettoyage fenêtres Saint-Pierre-d'Irube, vitrerie Saint-Pierre-d'Irube | O87: Lavage & nettoyage vitres Saint-Pierre-d'Irube | P87: Laveur de vitres à Saint-Pierre-d'Irube : lavage et nettoyage de vitres, baies vitrées, vitrines et vitres en hauteur (perche 13 m). Particuliers et pros.… | Q87: Lavage et nettoyage de vitres à Saint-Pierre-d'Irube | R87: Laveur de vitres à Saint-Pierre-d'Irube : particuliers et professionnels | Lavage des vitres, baies vitrées, vérandas, vitrines | Pollution urbaine et trafic | Vitres en hauteur : perche à eau pure jusqu'à 13 m, nacelle si besoin | Communes voisines : Mouguerre, Villefranque, Urcuit | Devis gratuit | S87: la poussière urbaine, le trafic et la pollution grisent vite vitrines, façades et baies vitrées | T87: Page déjà en ligne : l'enrichir (600 mots mini), ajouter tous les mots-clés et les liens vers les nouvelles pages de la ville | V87: lavage-vitres-saint-pierre-d-irube | W87: ="https://www.nettoyage-vitres-bayonne.fr/"&V87 | X87: entreprise-nettoyage-vitres-saint-pierre-d-irube, zone-intervention, contact-devis | Y87: À créer
A88: 87 | B88: 46301 | C88: Mardi | D88: S02 | E88: Optimisation | F88: 2 · Pages villes (1 par ville) | G88: Mixte | H88: Optimisation page existante | I88: Mouguerre | J88: 5428 | K88: BAB urbain (64) | L88: Vitres (tous mots-clés) | M88: Lavage vitres Mouguerre | N88: nettoyage vitres Mouguerre, laveur de vitres Mouguerre, nettoyeur de vitres Mouguerre, nettoyage fenêtres Mouguerre, vitrerie Mouguerre | O88: Lavage & nettoyage vitres Mouguerre | ProVitres-64 | P88: Laveur de vitres à Mouguerre : lavage et nettoyage de vitres, baies vitrées, vitrines et vitres en hauteur (perche 13 m). Particuliers et pros. Devis gratuit. | Q88: Lavage et nettoyage de vitres à Mouguerre | R88: Laveur de vitres à Mouguerre : particuliers et professionnels | Lavage des vitres, baies vitrées, vérandas, vitrines | Pollution urbaine et trafic | Vitres en hauteur : perche à eau pure jusqu'à 13 m, nacelle si besoin | Communes voisines : Saint-Pierre-d'Irube, Villefranque, Urcuit | Devis gratuit | S88: la poussière urbaine, le trafic et la pollution grisent vite vitrines, façades et baies vitrées | T88: Page déjà en ligne : l'enrichir (600 mots mini), ajouter tous les mots-clés et les liens vers les nouvelles pages de la ville | V88: lavage-vitres-mouguerre | W88: ="https://www.nettoyage-vitres-bayonne.fr/"&V88 | X88: entreprise-nettoyage-vitres-mouguerre, zone-intervention, contact-devis | Y88: À créer
A89: 88 | B89: 46301 | C89: Mardi | D89: S02 | E89: Optimisation | F89: 2 · Pages villes (1 par ville) | G89: Mixte | H89: Optimisation page existante | I89: Ascain | J89: 4658 | K89: Labourd intérieur (64) | L89: Vitres (tous mots-clés) | M89: Lavage vitres Ascain | N89: nettoyage vitres Ascain, laveur de vitres Ascain, nettoyeur de vitres Ascain, nettoyage fenêtres Ascain, vitrerie Ascain | O89: Lavage & nettoyage vitres Ascain | ProVitres-64 | P89: Laveur de vitres à Ascain : lavage et nettoyage de vitres, baies vitrées, vitrines et vitres en hauteur (perche 13 m). Particuliers et pros. Devis gratuit. | Q89: Lavage et nettoyage de vitres à Ascain | R89: Laveur de vitres à Ascain : particuliers et professionnels | Lavage des vitres, baies vitrées, vérandas, vitrines | Pollen, poussière agricole et calcaire | Vitres en hauteur : perche à eau pure jusqu'à 13 m, nacelle si besoin | Communes voisines : Saint-Pée-sur-Nivelle, Sare, Ustaritz | Devis gratuit | S89: maisons labourdines aux menuiseries colorées, pollen, poussière des champs et eau calcaire laissent des traces | T89: Page déjà en ligne : l'enrichir (600 mots mini), ajouter tous les mots-clés et les liens vers les nouvelles pages de la ville | V89: lavage-vitres-ascain | W89: ="https://www.nettoyage-vitres-bayonne.fr/"&V89 | X89: entreprise-nettoyage-vitres-ascain, zone-intervention, contact-devis | Y89: À créer
A90: 89 | B90: 46301 | C90: Mardi | D90: S02 | E90: Article | F90: Articles | G90: B2B | H90: Article métier B2B | L90: Conciergeries & locations saisonnières | M90: fréquence nettoyage vitres location saisonnière | O90: À quelle fréquence nettoyer les vitres de vos locations | P90: À quelle fréquence nettoyer les vitres de vos locations saisonnières ? — les conseils de ProVitres-64, laveur de vitres professionnel au Pays Basque et… | Q90: À quelle fréquence nettoyer les vitres de vos locations saisonnières ? | R90: Introduction | Le problème | Les solutions | Notre méthode | Conclusion + demande de devis | V90: blog-actus/a-quelle-frequence-nettoyer-les-vitres-de-vos-locations-saisonnieres | W90: ="https://www.nettoyage-vitres-bayonne.fr/"&V90 | X90: blog-actus, contact-devis | Y90: À créer
A91: 90 | B91: 46301 | C91: Mardi | D91: S02 | E91: Article | F91: Articles | G91: B2B | H91: Article métier B2B | L91: Écoles, collèges & crèches | M91: fréquence nettoyage vitres école | O91: À quelle fréquence nettoyer les vitres de votre | P91: À quelle fréquence nettoyer les vitres de votre établissement scolaire ? — les conseils de ProVitres-64, laveur de vitres professionnel au Pays Basque et… | Q91: À quelle fréquence nettoyer les vitres de votre établissement scolaire ? | R91: Introduction | Le problème | Les solutions | Notre méthode | Conclusion + demande de devis | V91: blog-actus/a-quelle-frequence-nettoyer-les-vitres-de-votre-etablissement-scolaire | W91: ="https://www.nettoyage-vitres-bayonne.fr/"&V91 | X91: blog-actus, contact-devis | Y91: À créer
A92: 91 | B92: 46302 | C92: Mercredi | D92: S02 | E92: Optimisation | F92: 2 · Pages villes (1 par ville) | G92: Mixte | H92: Optimisation page existante | I92: Seignosse | J92: 4056 | K92: Côte landaise (40) | L92: Vitres (tous mots-clés) | M92: Lavage vitres Seignosse | N92: nettoyage vitres Seignosse, laveur de vitres Seignosse, nettoyeur de vitres Seignosse, nettoyage fenêtres Seignosse, vitrerie Seignosse | O92: Lavage & nettoyage vitres Seignosse | ProVitres-64 | P92: Laveur de vitres à Seignosse : lavage et nettoyage de vitres, baies vitrées, vitrines et vitres en hauteur (perche 13 m). Particuliers et pros. Devis gratuit. | Q92: Lavage et nettoyage de vitres à Seignosse | R92: Laveur de vitres à Seignosse : particuliers et professionnels | Lavage des vitres, baies vitrées, vérandas, vitrines | Sable, sel et pollen de pin | Vitres en hauteur : perche à eau pure jusqu'à 13 m, nacelle si besoin | Communes voisines : Capbreton, Soustons, Labenne | Devis gratuit | S92: le sable, le sel et le pollen de pin forment un film collant sur les baies vitrées des villas et résidences | T92: Page déjà en ligne : l'enrichir (600 mots mini), ajouter tous les mots-clés et les liens vers les nouvelles pages de la ville | V92: lavage-vitres-seignosse | W92: ="https://www.nettoyage-vitres-bayonne.fr/"&V92 | X92: entreprise-nettoyage-vitres-seignosse, zone-intervention, contact-devis | Y92: À créer
A93: 92 | B93: 46302 | C93: Mercredi | D93: S02 | E93: Page hors menu | F93: 2 · Pages villes (1 par ville) | G93: Mixte | H93: Page ville principale | I93: Hossegor | J93: 3817 | K93: Côte landaise (40) | L93: Vitres (tous mots-clés) | M93: Nettoyage vitres Hossegor | N93: lavage vitres Hossegor, laveur de vitres Hossegor, nettoyeur de vitres Hossegor, nettoyage fenêtres Hossegor, vitrerie Hossegor | O93: Nettoyage & lavage vitres Hossegor | ProVitres-64 | P93: Laveur de vitres à Hossegor (40150) : nettoyage et lavage de vitres, baies vitrées, vitrines et vitres en hauteur. Particuliers et pros. Devis gratuit. | Q93: Nettoyage et lavage de vitres à Hossegor | R93: Laveur de vitres à Hossegor : particuliers et professionnels | Lavage des vitres, baies vitrées, vérandas, vitrines | Sable, sel et pollen de pin | Vitres en hauteur : perche à eau pure jusqu'à 13 m, nacelle si besoin | Communes voisines : Capbreton, Soustons, Labenne | Devis gratuit | S93: le sable, le sel et le pollen de pin forment un film collant sur les baies vitrées des villas et résidences | T93: Vitres en hauteur : perche à eau pure jusqu'à 13 m, nacelle si besoin | V93: nettoyage-vitres-hossegor | W93: ="https://www.nettoyage-vitres-bayonne.fr/"&V93 | X93: zone-intervention, contact-devis | Y93: À créer
A94: 93 | B94: 46302 | C94: Mercredi | D94: S02 | E94: Page hors menu | F94: 2 · Pages villes (1 par ville) | G94: Mixte | H94: Page ville principale | I94: Bénesse-Maremne | J94: 3780 | K94: Landes intérieures (40) | L94: Vitres (tous mots-clés) | M94: Nettoyage vitres Bénesse-Maremne | N94: lavage vitres Bénesse-Maremne, laveur de vitres Bénesse-Maremne, nettoyeur de vitres Bénesse-Maremne, nettoyage fenêtres Bénesse-Maremne, vitrerie Bénesse-Maremne | O94: Nettoyage & lavage vitres Bénesse-Maremne | ProVitres-64 | P94: Laveur de vitres à Bénesse-Maremne (40230) : nettoyage et lavage de vitres, baies vitrées, vitrines et vitres en hauteur. Particuliers et pros. Devis gratuit. | Q94: Nettoyage et lavage de vitres à Bénesse-Maremne | R94: Laveur de vitres à Bénesse-Maremne : particuliers et professionnels | Lavage des vitres, baies vitrées, vérandas, vitrines | Pollen de pin et résine | Vitres en hauteur : perche à eau pure jusqu'à 13 m, nacelle si besoin | Communes voisines : Saint-Vincent-de-Tyrosse, Tosse, Saint-Geours-de-Maremne | Devis gratuit | S94: le pollen de pin au printemps (dépôt jaune) et la résine de la forêt landaise encrassent les vitrages | T94: Vitres en hauteur : perche à eau pure jusqu'à 13 m, nacelle si besoin | V94: nettoyage-vitres-benesse-maremne | W94: ="https://www.nettoyage-vitres-bayonne.fr/"&V94 | X94: zone-intervention, contact-devis | Y94: À créer
A95: 94 | B95: 46302 | C95: Mercredi | D95: S02 | E95: Page hors menu | F95: 2 · Pages villes (1 par ville) | G95: Mixte | H95: Page ville principale | I95: Peyrehorade | J95: 3700 | K95: Pays d'Orthe (40) | L95: Vitres (tous mots-clés) | M95: Nettoyage vitres Peyrehorade | N95: lavage vitres Peyrehorade, laveur de vitres Peyrehorade, nettoyeur de vitres Peyrehorade, nettoyage fenêtres Peyrehorade, vitrerie Peyrehorade | O95: Nettoyage & lavage vitres Peyrehorade | ProVitres-64 | P95: Laveur de vitres à Peyrehorade (40300) : nettoyage et lavage de vitres, baies vitrées, vitrines et vitres en hauteur. Particuliers et pros. Devis gratuit. | Q95: Nettoyage et lavage de vitres à Peyrehorade | R95: Laveur de vitres à Peyrehorade : particuliers et professionnels | Lavage des vitres, baies vitrées, vérandas, vitrines | Brouillards de l'Adour et des gaves | Vitres en hauteur : perche à eau pure jusqu'à 13 m, nacelle si besoin | Communes voisines : Labatut, Saint-Lon-les-Mines, Port-de-Lanne | Devis gratuit | S95: l'humidité et les brouillards matinaux de l'Adour et des gaves laissent des traces sur les vitres | T95: Vitres en hauteur : perche à eau pure jusqu'à 13 m, nacelle si besoin | V95: nettoyage-vitres-peyrehorade | W95: ="https://www.nettoyage-vitres-bayonne.fr/"&V95 | X95: zone-intervention, contact-devis | Y95: À créer
A96: 95 | B96: 46302 | C96: Mercredi | D96: S02 | E96: Page hors menu | F96: 2 · Pages villes (1 par ville) | G96: Mixte | H96: Page ville principale | I96: Arcangues | J96: 3657 | K96: BAB urbain (64) | L96: Vitres (tous mots-clés) | M96: Nettoyage vitres Arcangues | N96: lavage vitres Arcangues, laveur de vitres Arcangues, nettoyeur de vitres Arcangues, nettoyage fenêtres Arcangues, vitrerie Arcangues | O96: Nettoyage & lavage vitres Arcangues | ProVitres-64 | P96: Laveur de vitres à Arcangues (64200) : nettoyage et lavage de vitres, baies vitrées, vitrines et vitres en hauteur. Particuliers et pros. Devis gratuit. | Q96: Nettoyage et lavage de vitres à Arcangues | R96: Laveur de vitres à Arcangues : particuliers et professionnels | Lavage des vitres, baies vitrées, vérandas, vitrines | Pollution urbaine et trafic | Vitres en hauteur : perche à eau pure jusqu'à 13 m, nacelle si besoin | Communes voisines : Bassussarry, Bayonne, Tarnos | Devis gratuit | S96: la poussière urbaine, le trafic et la pollution grisent vite vitrines, façades et baies vitrées | T96: Vitres en hauteur : perche à eau pure jusqu'à 13 m, nacelle si besoin | V96: nettoyage-vitres-arcangues | W96: ="https://www.nettoyage-vitres-bayonne.fr/"&V96 | X96: zone-intervention, contact-devis | Y96: À créer
A97: 96 | B97: 46302 | C97: Mercredi | D97: S02 | E97: Page hors menu | F97: 2 · Pages villes (1 par ville) | G97: Mixte | H97: Page ville principale | I97: Tosse | J97: 3556 | K97: Landes intérieures (40) | L97: Vitres (tous mots-clés) | M97: Nettoyage vitres Tosse | N97: lavage vitres Tosse, laveur de vitres Tosse, nettoyeur de vitres Tosse, nettoyage fenêtres Tosse, vitrerie Tosse | O97: Nettoyage & lavage vitres Tosse | ProVitres-64 | P97: Laveur de vitres à Tosse (40230) : nettoyage et lavage de vitres, baies vitrées, vitrines et vitres en hauteur. Particuliers et pros. Devis gratuit. | Q97: Nettoyage et lavage de vitres à Tosse | R97: Laveur de vitres à Tosse : particuliers et professionnels | Lavage des vitres, baies vitrées, vérandas, vitrines | Pollen de pin et résine | Vitres en hauteur : perche à eau pure jusqu'à 13 m, nacelle si besoin | Communes voisines : Saint-Vincent-de-Tyrosse, Bénesse-Maremne, Saint-Geours-de-Maremne | Devis gratuit | S97: le pollen de pin au printemps (dépôt jaune) et la résine de la forêt landaise encrassent les vitrages | T97: Vitres en hauteur : perche à eau pure jusqu'à 13 m, nacelle si besoin | V97: nettoyage-vitres-tosse | W97: ="https://www.nettoyage-vitres-bayonne.fr/"&V97 | X97: zone-intervention, contact-devis | Y97: À créer
A98: 97 | B98: 46302 | C98: Mercredi | D98: S02 | E98: Page hors menu | F98: 2 · Pages villes (1 par ville) | G98: Mixte | H98: Page ville principale | I98: Bassussarry | J98: 3414 | K98: BAB urbain (64) | L98: Vitres (tous mots-clés) | M98: Nettoyage vitres Bassussarry | N98: lavage vitres Bassussarry, laveur de vitres Bassussarry, nettoyeur de vitres Bassussarry, nettoyage fenêtres Bassussarry, vitrerie Bassussarry | O98: Nettoyage & lavage vitres Bassussarry | ProVitres-64 | P98: Laveur de vitres à Bassussarry (64200) : nettoyage et lavage de vitres, baies vitrées, vitrines et vitres en hauteur. Particuliers et pros. Devis gratuit. | Q98: Nettoyage et lavage de vitres à Bassussarry | R98: Laveur de vitres à Bassussarry : particuliers et professionnels | Lavage des vitres, baies vitrées, vérandas, vitrines | Pollution urbaine et trafic | Vitres en hauteur : perche à eau pure jusqu'à 13 m, nacelle si besoin | Communes voisines : Arcangues, Bayonne, Tarnos | Devis gratuit | S98: la poussière urbaine, le trafic et la pollution grisent vite vitrines, façades et baies vitrées | T98: Vitres en hauteur : perche à eau pure jusqu'à 13 m, nacelle si besoin | V98: nettoyage-vitres-bassussarry | W98: ="https://www.nettoyage-vitres-bayonne.fr/"&V98 | X98: zone-intervention, contact-devis | Y98: À créer
A99: 98 | B99: 46302 | C99: Mercredi | D99: S02 | E99: Page hors menu | F99: 2 · Pages villes (1 par ville) | G99: Mixte | H99: Page ville principale | I99: Saint-Vincent-de-Paul | J99: 3402 | K99: Landes intérieures (40) | L99: Vitres (tous mots-clés) | M99: Nettoyage vitres Saint-Vincent-de-Paul | N99: lavage vitres Saint-Vincent-de-Paul, laveur de vitres Saint-Vincent-de-Paul, nettoyeur de vitres Saint-Vincent-de-Paul, nettoyage fenêtres Saint-Vincent-de-Paul, vitrerie Saint-Vincent-de-Paul | O99: Nettoyage & lavage vitres Saint-Vincent-de-Paul | P99: Laveur de vitres à Saint-Vincent-de-Paul (40990) : nettoyage et lavage de vitres, baies vitrées, vitrines et vitres en hauteur. Particuliers et pros.… | Q99: Nettoyage et lavage de vitres à Saint-Vincent-de-Paul | R99: Laveur de vitres à Saint-Vincent-de-Paul : particuliers et professionnels | Lavage des vitres, baies vitrées, vérandas, vitrines | Pollen de pin et résine | Vitres en hauteur : perche à eau pure jusqu'à 13 m, nacelle si besoin | Communes voisines : Mées, Herm, Téthieu | Devis gratuit | S99: le pollen de pin au printemps (dépôt jaune) et la résine de la forêt landaise encrassent les vitrages | T99: Vitres en hauteur : perche à eau pure jusqu'à 13 m, nacelle si besoin | V99: nettoyage-vitres-saint-vincent-de-paul | W99: ="https://www.nettoyage-vitres-bayonne.fr/"&V99 | X99: zone-intervention, contact-devis | Y99: À créer
A100: 99 | B100: 46302 | C100: Mercredi | D100: S02 | E100: Article | F100: Articles | G100: B2B | H100: Article métier B2B | L100: Agences immobilières | M100: fréquence nettoyage vitres agence immobilière | O100: À quelle fréquence nettoyer les vitres de votre agence | P100: À quelle fréquence nettoyer les vitres de votre agence immobilière ? — les conseils de ProVitres-64, laveur de vitres professionnel au Pays Basque et dans… | Q100: À quelle fréquence nettoyer les vitres de votre agence immobilière ? | R100: Introduction | Le problème | Les solutions | Notre méthode | Conclusion + demande de devis | V100: blog-actus/a-quelle-frequence-nettoyer-les-vitres-de-votre-agence-immobiliere | W100: ="https://www.nettoyage-vitres-bayonne.fr/"&V100 | X100: blog-actus, contact-devis | Y100: À créer
...

Sheet Villes
A1: Rang | B1: Commune (usage SEO) | C1: Nom officiel | D1: Population | E1: Code postal | F1: Département | G1: Intercommunalité | H1: Tranche | I1: Secteur | J1: Angle local | K1: Communes voisines (liens)
A2: 1 | B2: Bayonne | C2: Bayonne | D2: 54306 | E2: 64100 | F2: Pyrénées-Atlantiques (64) | G2: Pays Basque | H2: A · > 10 000 hab. | I2: BAB urbain | J2: la poussière urbaine, le trafic et la pollution grisent vite vitrines, façades et baies vitrées | K2: Tarnos, Boucau, Saint-Pierre-d'Irube
A3: 2 | B3: Anglet | C3: Anglet | D3: 43271 | E3: 64600 | F3: Pyrénées-Atlantiques (64) | G3: Pays Basque | H3: A · > 10 000 hab. | I3: Côte basque | J3: les embruns salés et le sable soulevé par le vent ternissent les vitres face à l'océan en quelques semaines | K3: Biarritz, Hendaye, Saint-Jean-de-Luz
A4: 3 | B4: Biarritz | C4: Biarritz | D4: 26206 | E4: 64200 | F4: Pyrénées-Atlantiques (64) | G4: Pays Basque | H4: A · > 10 000 hab. | I4: Côte basque | J4: les embruns salés et le sable soulevé par le vent ternissent les vitres face à l'océan en quelques semaines | K4: Anglet, Hendaye, Saint-Jean-de-Luz
A5: 4 | B5: Dax | C5: Dax | D5: 22109 | E5: 40100 | F5: Landes (40) | G5: Grand Dax | H5: A · > 10 000 hab. | I5: Dax thermal | J5: hôtels, résidences de curistes et établissements de soins demandent des vitres irréprochables malgré une eau très calcaire | K5: Saint-Paul-lès-Dax
A6: 5 | B6: Hendaye | C6: Hendaye | D6: 18102 | E6: 64700 | F6: Pyrénées-Atlantiques (64) | G6: Pays Basque | H6: A · > 10 000 hab. | I6: Côte basque | J6: les embruns salés et le sable soulevé par le vent ternissent les vitres face à l'océan en quelques semaines | K6: Anglet, Biarritz, Saint-Jean-de-Luz
A7: 6 | B7: Saint-Jean-de-Luz | C7: Saint-Jean-de-Luz | D7: 14857 | E7: 64500 | F7: Pyrénées-Atlantiques (64) | G7: Pays Basque | H7: A · > 10 000 hab. | I7: Côte basque | J7: les embruns salés et le sable soulevé par le vent ternissent les vitres face à l'océan en quelques semaines | K7: Ciboure, Anglet, Biarritz
A8: 7 | B8: Saint-Paul-lès-Dax | C8: Saint-Paul-lès-Dax | D8: 14481 | E8: 40990 | F8: Landes (40) | G8: Grand Dax | H8: A · > 10 000 hab. | I8: Dax thermal | J8: hôtels, résidences de curistes et établissements de soins demandent des vitres irréprochables malgré une eau très calcaire | K8: Dax
A9: 8 | B9: Tarnos | C9: Tarnos | D9: 12957 | E9: 40220 | F9: Landes (40) | G9: Seignanx | H9: A · > 10 000 hab. | I9: BAB urbain | J9: la poussière urbaine, le trafic et la pollution grisent vite vitrines, façades et baies vitrées | K9: Bayonne, Boucau, Saint-Pierre-d'Irube
A10: 9 | B10: Urrugne | C10: Urrugne | D10: 10661 | E10: 64122 | F10: Pyrénées-Atlantiques (64) | G10: Pays Basque | H10: A · > 10 000 hab. | I10: Côte basque | J10: les embruns salés et le sable soulevé par le vent ternissent les vitres face à l'océan en quelques semaines | K10: Anglet, Biarritz, Hendaye
A11: 10 | B11: Capbreton | C11: Capbreton | D11: 9184 | E11: 40130 | F11: Landes (40) | G11: MACS | H11: B · 5 000–10 000 | I11: Côte landaise | J11: le sable, le sel et le pollen de pin forment un film collant sur les baies vitrées des villas et résidences | K11: Soustons, Labenne, Ondres
A12: 11 | B12: Boucau | C12: Boucau | D12: 8968 | E12: 64340 | F12: Pyrénées-Atlantiques (64) | G12: Pays Basque | H12: B · 5 000–10 000 | I12: BAB urbain | J12: la poussière urbaine, le trafic et la pollution grisent vite vitrines, façades et baies vitrées | K12: Bayonne, Tarnos, Saint-Pierre-d'Irube
A13: 12 | B13: Soustons | C13: Soustons | D13: 8701 | E13: 40140 | F13: Landes (40) | G13: MACS | H13: B · 5 000–10 000 | I13: Côte landaise | J13: le sable, le sel et le pollen de pin forment un film collant sur les baies vitrées des villas et résidences | K13: Azur, Capbreton, Labenne
... A234: 233 | B234: L'Hôpital-Saint-Blaise | C234: L'Hôpital-Saint-Blaise | D234: 55 | E234: 64130 | F234: Pyrénées-Atlantiques (64) | G234: Pays Basque | H234: E · < 1 000 | I234: Montagne basque | J234: humidité, mousses et vitrages difficiles d'accès sur les maisons de montagne et bâtiments anciens | K234: Mauléon-Licharre, Chéraute, Viodos-Abense-de-Bas
A236: Source : populations municipales INSEE via le référentiel officiel du découpage administratif (Etalab). Zone = CA Pays Basque + CC Seignanx, MACS, Grand Dax, Orthe et Arrigans.

Sheet Pages existantes
A1: URL existante | B1: Type | C1: Action conseillée
A2: https://www.nettoyage-vitres-bayonne.fr/blog-actus | B2: Page | C2: Garder. Y ajouter des liens vers les nouvelles pages du même thème.
A3: https://www.nettoyage-vitres-bayonne.fr/contact-devis | B3: Page | C3: Garder. Y ajouter des liens vers les nouvelles pages du même thème.
A4: https://www.nettoyage-vitres-bayonne.fr/lavage-vitres-anglet | B4: Page ville | C4: Page ville principale : à optimiser (voir ligne « Optimisation » du calendrier). Ne pas créer de page nettoyage-vitres-[même ville].
A5: https://www.nettoyage-vitres-bayonne.fr/lavage-vitres-ascain | B5: Page ville | C5: Page ville principale : à optimiser (voir ligne « Optimisation » du calendrier). Ne pas créer de page nettoyage-vitres-[même ville].
A6: https://www.nettoyage-vitres-bayonne.fr/lavage-vitres-bayonne | B6: Page ville | C6: Page ville principale : à optimiser (voir ligne « Optimisation » du calendrier). Ne pas créer de page nettoyage-vitres-[même ville].
A7: https://www.nettoyage-vitres-bayonne.fr/lavage-vitres-biarritz | B7: Page ville | C7: Page ville principale : à optimiser (voir ligne « Optimisation » du calendrier). Ne pas créer de page nettoyage-vitres-[même ville].
A8: https://www.nettoyage-vitres-bayonne.fr/lavage-vitres-bidart | B8: Page ville | C8: Page ville principale : à optimiser (voir ligne « Optimisation » du calendrier). Ne pas créer de page nettoyage-vitres-[même ville].
A9: https://www.nettoyage-vitres-bayonne.fr/lavage-vitres-boucau | B9: Page ville | C9: Page ville principale : à optimiser (voir ligne « Optimisation » du calendrier). Ne pas créer de page nettoyage-vitres-[même ville].
A10: https://www.nettoyage-vitres-bayonne.fr/lavage-vitres-cambo-les-bains | B10: Page ville | C10: Page ville principale : à optimiser (voir ligne « Optimisation » du calendrier). Ne pas créer de page nettoyage-vitres-[même ville].
A11: https://www.nettoyage-vitres-bayonne.fr/lavage-vitres-ciboure | B11: Page ville | C11: Page ville principale : à optimiser (voir ligne « Optimisation » du calendrier). Ne pas créer de page nettoyage-vitres-[même ville].
A12: https://www.nettoyage-vitres-bayonne.fr/lavage-vitres-dax | B12: Page ville | C12: Page ville principale : à optimiser (voir ligne « Optimisation » du calendrier). Ne pas créer de page nettoyage-vitres-[même ville].
... A40: https://www.nettoyage-vitres-bayonne.fr/blog-actus/combien-cote-le-nettoyage-de-vitres-bayonne | B40: Article | C40: Garder. Ajouter des liens vers les pages ville et segment correspondantes.
A42: Relevé depuis le sitemap du site le 27/09/2026. Aucune de ces URL n'est reprise dans le calendrier.

Sheet Métiers & mots-clés
A1: Métier B2B | B1: Mot-clé de base | C1: URL type | D1: Villes couvertes | E1: Point fort à mettre en avant
A2: Mairies & bâtiments communaux | B2: Nettoyage vitres mairie | C2: nettoyage-vitres-mairie-[ville] | D2: > 10 000 hab., 5 000–10 000, 2 000–5 000 | E2: Devis par bâtiment, facturation Chorus Pro, interventions pendant les vacances scolaires
A3: Immeubles & copropriétés | B3: Nettoyage vitres immeuble | C3: nettoyage-vitres-immeuble-[ville] | D3: > 10 000 hab., 5 000–10 000, 2 000–5 000 (littoral) | E3: Façades et parties communes en hauteur sans nacelle (perche 13 m), facture par immeuble pour les syndics
A4: Vitres en hauteur | B4: Nettoyage vitres en hauteur | C4: nettoyage-vitres-en-hauteur-[ville] | D4: > 10 000 hab. | E4: Perche télescopique eau pure 13 m, nacelle, formation travail en hauteur
A5: Commerces & boutiques | B5: Nettoyage vitrine magasin | C5: nettoyage-vitrine-magasin-[ville] | D5: > 10 000 hab., 5 000–10 000, 2 000–5 000 | E5: Passage avant l'ouverture, abonnement vitrine, tournée à vélo
A6: Hôtels & résidences | B6: Nettoyage vitres hôtel | C6: nettoyage-vitres-hotel-[ville] | D6: > 10 000 hab., 5 000–10 000, 2 000–5 000 (littoral) | E6: Façades et baies des chambres en hauteur, interventions hors affluence, renfort avant la saison
A7: Bureaux & entreprises | B7: Nettoyage vitres bureaux | C7: nettoyage-vitres-bureaux-[ville] | D7: > 10 000 hab., 5 000–10 000, 2 000–5 000 | E7: Contrat d'entretien, interventions hors horaires, façades vitrées
A8: Restaurants, bars & cafés | B8: Nettoyage vitres restaurant | C8: nettoyage-vitres-restaurant-[ville] | D8: > 10 000 hab., 5 000–10 000, 2 000–5 000 | E8: Vitrine et terrasse vitrée propres avant le service
A9: Conciergeries & locations saisonnières | B9: Nettoyage vitres location saisonnière | C9: nettoyage-vitres-location-saisonniere-[ville] | D9: > 10 000 hab., 5 000–10 000, 2 000–5 000 (littoral) | E9: Passages entre deux séjours, baies vitrées face à la mer
A10: Écoles, collèges & crèches | B10: Nettoyage vitres école | C10: nettoyage-vitres-ecole-[ville] | D10: > 10 000 hab., 5 000–10 000 | E10: Interventions pendant les vacances, verrières et préaux
A11: Agences immobilières | B11: Nettoyage vitres agence immobilière | C11: nettoyage-vitres-agence-immobiliere-[ville] | D11: > 10 000 hab., 5 000–10 000 | E11: Vitres propres avant photos et visites, tarif partenaire
A12: Cabinets médicaux & paramédicaux | B12: Nettoyage vitres cabinet médical | C12: nettoyage-vitres-cabinet-medical-[ville] | D12: > 10 000 hab., 5 000–10 000 | E12: Interventions hors consultations, image d'hygiène
... A25: Ports & capitaineries | B25: Nettoyage vitres port | C25: nettoyage-vitres-port-[ville] | D25: Capbreton, Saint-Jean-de-Luz, Hendaye, Anglet, Bayonne, Ciboure | E25: Sel et embruns
A28: Mots-clés : où va chacun ?
A29: Mot-clé | B29: Où il est travaillé
A30: Nettoyage vitres [ville] | B30: Page ville principale (mot-clé du Title/H1)
A31: Lavage vitres [ville] | B31: Page ville principale (H2 + texte) — Title/H1 sur les 18 pages existantes
A32: Laveur de vitres [ville] | B32: Page ville principale (H2 + texte), pages secteur (Title)
A33: Nettoyeur de vitres [ville] | B33: Page ville principale (texte), articles
A34: Nettoyage fenêtres [ville] | B34: Page ville principale (texte) + pilier « Nettoyage fenêtres »
A35: Vitrerie [ville] | B35: Page pro par ville (texte) — préciser qu'il s'agit de nettoyage, pas de pose
A36: Entreprise nettoyage vitres [ville] | B36: Page pro par ville (Title/H1)
A37: Nettoyage vitres en hauteur / immeuble [ville] | B37: Pages métier × ville + piliers dédiés + série d'articles
A38: Nettoyage vitres mairie [ville] / bâtiments publics | B38: Pages métier × ville + 5 pages intercommunalités + articles collectivités
A39: Miroirs, parois de douche, véranda, baie vitrée, maison, villa | B39: Phase particuliers (janvier–février)
A40: Panneaux solaires [ville] | B40: Villes de plus de 2 000 hab. + piliers pros / hangar agricole
